[{"id": "10080515", "voivodeship": "lodzkie", "subject": "his", "stage": "3", "year": "2018", "type": "test", "school": "gim"}, {"id": "52294755", "voivodeship": "lodzkie", "subject": "his", "stage": "1", "year": "2018", "type": "test", "school": "sp"}, {"id": "57230961", "voivodeship": "lodzkie", "subject": "his", "stage": "1", "year": "2018", "type": "test", "school": "gim"}, {"id": "58502473", "voivodeship": "lodzkie", "subject": "his", "stage": "3", "year": "2018", "type": "test", "school": "sp"}, {"id": "89067929", "voivodeship": "lodzkie", "subject": "his", "stage": "2", "year": "2018", "type": "test", "school": "gim"}, {"id": "90796196", "voivodeship": "lodzkie", "subject": "his", "stage": "2", "year": "2018", "type": "test", "school": "sp"}, {"id": "56238296", "voivodeship": "lodzkie", "subject": "his", "stage": "1", "year": "2019", "type": "test", "school": "sp"}, {"id": "59501212", "voivodeship": "lodzkie", "subject": "his", "stage": "3", "year": "2019", "type": "test", "school": "sp"}, {"id": "74609348", "voivodeship": "lodzkie", "subject": "his", "stage": "2", "year": "2019", "type": "test", "school": "sp"}, {"id": "19225624", "voivodeship": "lodzkie", "subject": "his", "stage": "2", "year": "2020", "type": "test", "school": "sp"}, {"id": "51294412", "voivodeship": "lodzkie", "subject": "his", "stage": "3", "year": "2020", "type": "test", "school": "sp"}, {"id": "77222614", "voivodeship": "lodzkie", "subject": "his", "stage": "1", "year": "2020", "type": "test", "school": "sp"}, {"id": "16157271", "voivodeship": "lodzkie", "subject": "his", "stage": "2", "year": "2021", "type": "test", "school": "sp"}, {"id": "23418927", "voivodeship": "lodzkie", "subject": "his", "stage": "2", "year": "2021", "type": "ans", "school": "sp"}, {"id": "41840025", "voivodeship": "lodzkie", "subject": "his", "stage": "1", "year": "2021", "type": "ans", "school": "sp"}, {"id": "42417854", "voivodeship": "lodzkie", "subject": "his", "stage": "3", "year": "2021", "type": "test", "school": "sp"}, {"id": "52269380", "voivodeship": "lodzkie", "subject": "his", "stage": "1", "year": "2021", "type": "test", "school": "sp"}, {"id": "90097255", "voivodeship": "lodzkie", "subject": "his", "stage": "3", "year": "2021", "type": "ans", "school": "sp"}, {"id": "43031854", "voivodeship": "lodzkie", "subject": "his", "stage": "3", "year": "2022", "type": "ans", "school": "sp"}, {"id": "48357582", "voivodeship": "lodzkie", "subject": "his", "stage": "3", "year": "2022", "type": "test", "school": "sp"}, {"id": "59355057", "voivodeship": "lodzkie", "subject": "his", "stage": "1", "year": "2022", "type": "ans", "school": "sp"}, {"id": "65839365", "voivodeship": "lodzkie", "subject": "his", "stage": "2", "year": "2022", "type": "ans", "school": "sp"}, {"id": "73158515", "voivodeship": "lodzkie", "subject": "his", "stage": "1", "year": "2022", "type": "test", "school": "sp"}, {"id": "92093117", "voivodeship": "lodzkie", "subject": "his", "stage": "2", "year": "2022", "type": "test", "school": "sp"}, {"id": "95047462", "type": "test", "year": "2021", "stage": "1", "subject": "che", "voivodeship": "lodzkie", "school": "sp"}, {"id": "94191499", "type": "test", "year": "2020", "stage": "2", "subject": "che", "voivodeship": "lodzkie", "school": "sp"}, {"id": "84940529", "type": "ans", "year": "2022", "stage": "2", "subject": "che", "voivodeship": "lodzkie", "school": "sp"}, {"id": "84636842", "type": "test", "year": "2020", "stage": "3", "subject": "che", "voivodeship": "lodzkie", "school": "sp"}, {"id": "84355943", "type": "test", "year": "2021", "stage": "3", "subject": "che", "voivodeship": "lodzkie", "school": "sp"}, {"id": "78112113", "type": "test", "year": "2022", "stage": "3", "subject": "che", "voivodeship": "lodzkie", "school": "sp"}, {"id": "77500554", "type": "ans", "year": "2021", "stage": "2", "subject": "che", "voivodeship": "lodzkie", "school": "sp"}, {"id": "76030023", "type": "ans", "year": "2021", "stage": "3", "subject": "che", "voivodeship": "lodzkie", "school": "sp"}, {"id": "72702781", "type": "test", "year": "2018", "stage": "2", "subject": "che", "voivodeship": "lodzkie", "school": "gim"}, {"id": "70669109", "type": "ans", "year": "2021", "stage": "1", "subject": "che", "voivodeship": "lodzkie", "school": "sp"}, {"id": "63618360", "type": "test", "year": "2018", "stage": "1", "subject": "che", "voivodeship": "lodzkie", "school": "gim"}, {"id": "63047330", "type": "test", "year": "2019", "stage": "2", "subject": "che", "voivodeship": "lodzkie", "school": "sp"}, {"id": "50023008", "type": "test", "year": "2019", "stage": "3", "subject": "che", "voivodeship": "lodzkie", "school": "sp"}, {"id": "41625038", "type": "test", "year": "2020", "stage": "1", "subject": "che", "voivodeship": "lodzkie", "school": "sp"}, {"id": "36477030", "type": "test", "year": "2022", "stage": "2", "subject": "che", "voivodeship": "lodzkie", "school": "sp"}, {"id": "35494081", "type": "ans", "year": "2022", "stage": "1", "subject": "che", "voivodeship": "lodzkie", "school": "sp"}, {"id": "33144624", "type": "test", "year": "2018", "stage": "3", "subject": "che", "voivodeship": "lodzkie", "school": "gim"}, {"id": "25952529", "type": "ans", "year": "2022", "stage": "3", "subject": "che", "voivodeship": "lodzkie", "school": "sp"}, {"id": "22662393", "type": "test", "year": "2019", "stage": "1", "subject": "che", "voivodeship": "lodzkie", "school": "sp"}, {"id": "18151607", "type": "test", "year": "2021", "stage": "2", "subject": "che", "voivodeship": "lodzkie", "school": "sp"}, {"id": "16426391", "type": "test", "year": "2022", "stage": "1", "subject": "che", "voivodeship": "lodzkie", "school": "sp"}, {"id": "11542938", "type": "test", "year": "2021", "stage": "1", "subject": "fiz", "voivodeship": "lodzkie", "school": "sp"}, {"id": "14073459", "type": "ans", "year": "2021", "stage": "1", "subject": "fiz", "voivodeship": "lodzkie", "school": "sp"}, {"id": "19823611", "type": "test", "year": "2019", "stage": "2", "subject": "fiz", "voivodeship": "lodzkie", "school": "sp"}, {"id": "21273078", "type": "ans", "year": "2021", "stage": "2", "subject": "fiz", "voivodeship": "lodzkie", "school": "sp"}, {"id": "21395573", "type": "test", "year": "2019", "stage": "1", "subject": "fiz", "voivodeship": "lodzkie", "school": "sp"}, {"id": "23191743", "type": "test", "year": "2021", "stage": "2", "subject": "fiz", "voivodeship": "lodzkie", "school": "sp"}, {"id": "26745181", "type": "ans", "year": "2021", "stage": "3", "subject": "fiz", "voivodeship": "lodzkie", "school": "sp"}, {"id": "29250683", "type": "test", "year": "2020", "stage": "1", "subject": "fiz", "voivodeship": "lodzkie", "school": "sp"}, {"id": "31361822", "type": "test", "year": "2018", "stage": "3", "subject": "fiz", "voivodeship": "lodzkie", "school": "gim"}, {"id": "35577556", "type": "test", "year": "2020", "stage": "2", "subject": "fiz", "voivodeship": "lodzkie", "school": "sp"}, {"id": "50589220", "type": "test", "year": "2022", "stage": "1", "subject": "fiz", "voivodeship": "lodzkie", "school": "sp"}, {"id": "52570749", "type": "ans", "year": "2022", "stage": "1", "subject": "fiz", "voivodeship": "lodzkie", "school": "sp"}, {"id": "55930416", "type": "test", "year": "2022", "stage": "2", "subject": "fiz", "voivodeship": "lodzkie", "school": "sp"}, {"id": "64117014", "type": "test", "year": "2020", "stage": "3", "subject": "fiz", "voivodeship": "lodzkie", "school": "sp"}, {"id": "76548283", "type": "test", "year": "2021", "stage": "3", "subject": "fiz", "voivodeship": "lodzkie", "school": "sp"}, {"id": "85551395", "type": "test", "year": "2018", "stage": "2", "subject": "fiz", "voivodeship": "lodzkie", "school": "gim"}, {"id": "88558591", "type": "ans", "year": "2022", "stage": "2", "subject": "fiz", "voivodeship": "lodzkie", "school": "sp"}, {"id": "95728091", "type": "test", "year": "2018", "stage": "1", "subject": "fiz", "voivodeship": "lodzkie", "school": "gim"}, {"id": "99275665", "type": "test", "year": "2019", "stage": "3", "subject": "fiz", "voivodeship": "lodzkie", "school": "sp"}, {"id": "12196160", "type": "test", "year": "2022", "stage": "3", "subject": "fiz", "voivodeship": "lodzkie", "school": "sp"}, {"id": "39602533", "type": "ans", "year": "2022", "stage": "3", "subject": "fiz", "voivodeship": "lodzkie", "school": "sp"}, {"id": "10627090", "type": "test", "year": "2021", "stage": "3", "subject": "bio", "voivodeship": "lodzkie", "school": "sp"}, {"id": "12372141", "type": "ans", "year": "2021", "stage": "3", "subject": "bio", "voivodeship": "lodzkie", "school": "sp"}, {"id": "14083660", "type": "ans", "year": "2022", "stage": "2", "subject": "bio", "voivodeship": "lodzkie", "school": "sp"}, {"id": "18632369", "type": "test", "year": "2021", "stage": "1", "subject": "bio", "voivodeship": "lodzkie", "school": "sp"}, {"id": "19697253", "type": "test", "year": "2022", "stage": "3", "subject": "bio", "voivodeship": "lodzkie", "school": "sp"}, {"id": "31519147", "type": "test", "year": "2018", "stage": "3", "subject": "bio", "voivodeship": "lodzkie", "school": "gim"}, {"id": "37804166", "type": "test", "year": "2018", "stage": "2", "subject": "bio", "voivodeship": "lodzkie", "school": "gim"}, {"id": "44631191", "type": "ans", "year": "2021", "stage": "2", "subject": "bio", "voivodeship": "lodzkie", "school": "sp"}, {"id": "54986393", "type": "test", "year": "2022", "stage": "1", "subject": "bio", "voivodeship": "lodzkie", "school": "sp"}, {"id": "61928400", "type": "test", "year": "2022", "stage": "2", "subject": "bio", "voivodeship": "lodzkie", "school": "sp"}, {"id": "62460564", "type": "test", "year": "2020", "stage": "1", "subject": "bio", "voivodeship": "lodzkie", "school": "sp"}, {"id": "65869174", "type": "ans", "year": "2022", "stage": "3", "subject": "bio", "voivodeship": "lodzkie", "school": "sp"}, {"id": "66829074", "type": "test", "year": "2020", "stage": "2", "subject": "bio", "voivodeship": "lodzkie", "school": "sp"}, {"id": "68323269", "type": "test", "year": "2018", "stage": "1", "subject": "bio", "voivodeship": "lodzkie", "school": "gim"}, {"id": "72745908", "type": "ans", "year": "2021", "stage": "1", "subject": "bio", "voivodeship": "lodzkie", "school": "sp"}, {"id": "74323533", "type": "test", "year": "2019", "stage": "3", "subject": "bio", "voivodeship": "lodzkie", "school": "sp"}, {"id": "80704148", "type": "ans", "year": "2022", "stage": "1", "subject": "bio", "voivodeship": "lodzkie", "school": "sp"}, {"id": "82398823", "type": "test", "year": "2019", "stage": "1", "subject": "bio", "voivodeship": "lodzkie", "school": "sp"}, {"id": "82658486", "type": "test", "year": "2020", "stage": "3", "subject": "bio", "voivodeship": "lodzkie", "school": "sp"}, {"id": "86830253", "type": "test", "year": "2019", "stage": "2", "subject": "bio", "voivodeship": "lodzkie", "school": "sp"}, {"id": "88597774", "type": "test", "year": "2021", "stage": "2", "subject": "bio", "voivodeship": "lodzkie", "school": "sp"}, {"id": "13551705", "type": "test", "year": "2022", "stage": "3", "subject": "mat", "voivodeship": "lodzkie", "school": "sp"}, {"id": "16215888", "type": "test", "year": "2019", "stage": "2", "subject": "mat", "voivodeship": "lodzkie", "school": "sp"}, {"id": "23681590", "type": "ans", "year": "2022", "stage": "1", "subject": "mat", "voivodeship": "lodzkie", "school": "sp"}, {"id": "27284840", "type": "test", "year": "2021", "stage": "2", "subject": "mat", "voivodeship": "lodzkie", "school": "sp"}, {"id": "28537936", "type": "test", "year": "2021", "stage": "1", "subject": "mat", "voivodeship": "lodzkie", "school": "sp"}, {"id": "31714123", "type": "test", "year": "2018", "stage": "3", "subject": "mat", "voivodeship": "lodzkie", "school": "gim"}, {"id": "33405057", "type": "test", "year": "2021", "stage": "3", "subject": "mat", "voivodeship": "lodzkie", "school": "sp"}, {"id": "41501226", "type": "test", "year": "2018", "stage": "1", "subject": "mat", "voivodeship": "lodzkie", "school": "gim"}, {"id": "52589197", "type": "test", "year": "2022", "stage": "2", "subject": "mat", "voivodeship": "lodzkie", "school": "sp"}, {"id": "53829177", "type": "test", "year": "2020", "stage": "3", "subject": "mat", "voivodeship": "lodzkie", "school": "sp"}, {"id": "56859913", "type": "ans", "year": "2022", "stage": "2", "subject": "mat", "voivodeship": "lodzkie", "school": "sp"}, {"id": "63761830", "type": "test", "year": "2019", "stage": "3", "subject": "mat", "voivodeship": "lodzkie", "school": "sp"}, {"id": "66480319", "type": "ans", "year": "2021", "stage": "3", "subject": "mat", "voivodeship": "lodzkie", "school": "sp"}, {"id": "68514509", "type": "test", "year": "2018", "stage": "3", "subject": "mat", "voivodeship": "lodzkie", "school": "sp"}, {"id": "74227276", "type": "test", "year": "2018", "stage": "2", "subject": "mat", "voivodeship": "lodzkie", "school": "sp"}, {"id": "76838059", "type": "test", "year": "2022", "stage": "1", "subject": "mat", "voivodeship": "lodzkie", "school": "sp"}, {"id": "81274076", "type": "test", "year": "2018", "stage": "1", "subject": "mat", "voivodeship": "lodzkie", "school": "sp"}, {"id": "84416469", "type": "ans", "year": "2022", "stage": "3", "subject": "mat", "voivodeship": "lodzkie", "school": "sp"}, {"id": "87023352", "type": "test", "year": "2018", "stage": "2", "subject": "mat", "voivodeship": "lodzkie", "school": "gim"}, {"id": "87939388", "type": "test", "year": "2020", "stage": "2", "subject": "mat", "voivodeship": "lodzkie", "school": "sp"}, {"id": "88244792", "type": "test", "year": "2019", "stage": "1", "subject": "mat", "voivodeship": "lodzkie", "school": "sp"}, {"id": "94151441", "type": "ans", "year": "2021", "stage": "2", "subject": "mat", "voivodeship": "lodzkie", "school": "sp"}, {"id": "95088415", "type": "test", "year": "2020", "stage": "1", "subject": "mat", "voivodeship": "lodzkie", "school": "sp"}, {"id": "98823981", "type": "ans", "year": "2021", "stage": "1", "subject": "mat", "voivodeship": "lodzkie", "school": "sp"}, {"id": "49529546", "type": "test", "year": "2018", "stage": "1", "subject": "mat", "voivodeship": "mazowieckie", "school": "sp"}, {"id": "77293769", "type": "test", "year": "2018", "stage": "1", "subject": "bio", "voivodeship": "mazowieckie", "school": "sp"}, {"id": "70277257", "type": "test", "year": "2018", "stage": "1", "subject": "fiz", "voivodeship": "mazowieckie", "school": "sp"}, {"id": "10866855", "type": "test", "year": "2018", "stage": "1", "subject": "geo", "voivodeship": "mazowieckie", "school": "sp"}, {"id": "50934327", "type": "test", "year": "2018", "stage": "1", "subject": "hip", "voivodeship": "mazowieckie", "school": "sp"}, {"id": "68311714", "type": "test", "year": "2018", "stage": "1", "subject": "fra", "voivodeship": "mazowieckie", "school": "sp"}, {"id": "27965511", "type": "test", "year": "2018", "stage": "1", "subject": "nie", "voivodeship": "mazowieckie", "school": "sp"}, {"id": "23654197", "type": "test", "year": "2018", "stage": "1", "subject": "ang", "voivodeship": "mazowieckie", "school": "sp"}, {"id": "75298184", "type": "test", "year": "2018", "stage": "1", "subject": "wos", "voivodeship": "mazowieckie", "school": "sp"}, {"id": "27257127", "type": "test", "year": "2018", "stage": "1", "subject": "che", "voivodeship": "mazowieckie", "school": "sp"}, {"id": "73843066", "type": "test", "year": "2018", "stage": "1", "subject": "pol", "voivodeship": "mazowieckie", "school": "sp"}, {"id": "24158926", "type": "test", "year": "2018", "stage": "1", "subject": "ros", "voivodeship": "mazowieckie", "school": "sp"}, {"id": "42918597", "type": "test", "year": "2018", "stage": "1", "subject": "his", "voivodeship": "mazowieckie", "school": "sp"}, {"id": "86401893", "type": "test", "year": "2018", "stage": "2", "subject": "mat", "voivodeship": "mazowieckie", "school": "sp"}, {"id": "34582559", "type": "test", "year": "2018", "stage": "2", "subject": "bio", "voivodeship": "mazowieckie", "school": "sp"}, {"id": "88013226", "type": "test", "year": "2018", "stage": "2", "subject": "fiz", "voivodeship": "mazowieckie", "school": "sp"}, {"id": "36118997", "type": "test", "year": "2018", "stage": "2", "subject": "geo", "voivodeship": "mazowieckie", "school": "sp"}, {"id": "96877896", "type": "test", "year": "2018", "stage": "2", "subject": "hip", "voivodeship": "mazowieckie", "school": "sp"}, {"id": "44925588", "type": "test", "year": "2018", "stage": "2", "subject": "fra", "voivodeship": "mazowieckie", "school": "sp"}, {"id": "46161480", "type": "test", "year": "2018", "stage": "2", "subject": "nie", "voivodeship": "mazowieckie", "school": "sp"}, {"id": "75658355", "type": "test", "year": "2018", "stage": "2", "subject": "ang", "voivodeship": "mazowieckie", "school": "sp"}, {"id": "93774983", "type": "test", "year": "2018", "stage": "2", "subject": "wos", "voivodeship": "mazowieckie", "school": "sp"}, {"id": "52336368", "type": "test", "year": "2018", "stage": "2", "subject": "che", "voivodeship": "mazowieckie", "school": "sp"}, {"id": "60147978", "type": "test", "year": "2018", "stage": "2", "subject": "pol", "voivodeship": "mazowieckie", "school": "sp"}, {"id": "95961257", "type": "test", "year": "2018", "stage": "2", "subject": "ros", "voivodeship": "mazowieckie", "school": "sp"}, {"id": "80915875", "type": "test", "year": "2018", "stage": "2", "subject": "his", "voivodeship": "mazowieckie", "school": "sp"}, {"id": "66243930", "type": "test", "year": "2018", "stage": "3", "subject": "mat", "voivodeship": "mazowieckie", "school": "sp"}, {"id": "92019716", "type": "test", "year": "2018", "stage": "3", "subject": "bio", "voivodeship": "mazowieckie", "school": "sp"}, {"id": "53854099", "type": "test", "year": "2018", "stage": "3", "subject": "fiz", "voivodeship": "mazowieckie", "school": "sp"}, {"id": "74045858", "type": "test", "year": "2018", "stage": "3", "subject": "geo", "voivodeship": "mazowieckie", "school": "sp"}, {"id": "35322725", "type": "test", "year": "2018", "stage": "3", "subject": "hip", "voivodeship": "mazowieckie", "school": "sp"}, {"id": "27636667", "type": "test", "year": "2018", "stage": "3", "subject": "fra", "voivodeship": "mazowieckie", "school": "sp"}, {"id": "40287973", "type": "test", "year": "2018", "stage": "3", "subject": "nie", "voivodeship": "mazowieckie", "school": "sp"}, {"id": "44395199", "type": "test", "year": "2018", "stage": "3", "subject": "ang", "voivodeship": "mazowieckie", "school": "sp"}, {"id": "39658366", "type": "test", "year": "2018", "stage": "3", "subject": "wos", "voivodeship": "mazowieckie", "school": "sp"}, {"id": "66733282", "type": "test", "year": "2018", "stage": "3", "subject": "che", "voivodeship": "mazowieckie", "school": "sp"}, {"id": "23404575", "type": "test", "year": "2018", "stage": "3", "subject": "pol", "voivodeship": "mazowieckie", "school": "sp"}, {"id": "92554777", "type": "test", "year": "2018", "stage": "3", "subject": "ros", "voivodeship": "mazowieckie", "school": "sp"}, {"id": "99392928", "type": "test", "year": "2018", "stage": "3", "subject": "his", "voivodeship": "mazowieckie", "school": "sp"}, {"id": "91545464", "type": "test", "year": "2018", "stage": "1", "subject": "mat", "voivodeship": "mazowieckie", "school": "gim"}, {"id": "54084312", "type": "test", "year": "2018", "stage": "1", "subject": "bio", "voivodeship": "mazowieckie", "school": "gim"}, {"id": "76336608", "type": "test", "year": "2018", "stage": "1", "subject": "fiz", "voivodeship": "mazowieckie", "school": "gim"}, {"id": "64916417", "type": "test", "year": "2018", "stage": "1", "subject": "geo", "voivodeship": "mazowieckie", "school": "gim"}, {"id": "78273202", "type": "test", "year": "2018", "stage": "1", "subject": "hip", "voivodeship": "mazowieckie", "school": "gim"}, {"id": "77087800", "type": "test", "year": "2018", "stage": "1", "subject": "fra", "voivodeship": "mazowieckie", "school": "gim"}, {"id": "96234815", "type": "test", "year": "2018", "stage": "1", "subject": "nie", "voivodeship": "mazowieckie", "school": "gim"}, {"id": "59403980", "type": "test", "year": "2018", "stage": "1", "subject": "ang", "voivodeship": "mazowieckie", "school": "gim"}, {"id": "61717957", "type": "test", "year": "2018", "stage": "1", "subject": "wos", "voivodeship": "mazowieckie", "school": "gim"}, {"id": "98084177", "type": "test", "year": "2018", "stage": "1", "subject": "che", "voivodeship": "mazowieckie", "school": "gim"}, {"id": "60176994", "type": "test", "year": "2018", "stage": "1", "subject": "pol", "voivodeship": "mazowieckie", "school": "gim"}, {"id": "54494835", "type": "test", "year": "2018", "stage": "1", "subject": "ros", "voivodeship": "mazowieckie", "school": "gim"}, {"id": "79248134", "type": "test", "year": "2018", "stage": "1", "subject": "his", "voivodeship": "mazowieckie", "school": "gim"}, {"id": "94439605", "type": "test", "year": "2018", "stage": "2", "subject": "mat", "voivodeship": "mazowieckie", "school": "gim"}, {"id": "60181707", "type": "test", "year": "2018", "stage": "2", "subject": "bio", "voivodeship": "mazowieckie", "school": "gim"}, {"id": "19683512", "type": "test", "year": "2018", "stage": "2", "subject": "fiz", "voivodeship": "mazowieckie", "school": "gim"}, {"id": "93616791", "type": "test", "year": "2018", "stage": "2", "subject": "geo", "voivodeship": "mazowieckie", "school": "gim"}, {"id": "16196237", "type": "test", "year": "2018", "stage": "2", "subject": "hip", "voivodeship": "mazowieckie", "school": "gim"}, {"id": "52207267", "type": "test", "year": "2018", "stage": "2", "subject": "fra", "voivodeship": "mazowieckie", "school": "gim"}, {"id": "15422828", "type": "test", "year": "2018", "stage": "2", "subject": "nie", "voivodeship": "mazowieckie", "school": "gim"}, {"id": "65465190", "type": "test", "year": "2018", "stage": "2", "subject": "ang", "voivodeship": "mazowieckie", "school": "gim"}, {"id": "80658314", "type": "test", "year": "2018", "stage": "2", "subject": "wos", "voivodeship": "mazowieckie", "school": "gim"}, {"id": "45080927", "type": "test", "year": "2018", "stage": "2", "subject": "che", "voivodeship": "mazowieckie", "school": "gim"}, {"id": "89664946", "type": "test", "year": "2018", "stage": "2", "subject": "pol", "voivodeship": "mazowieckie", "school": "gim"}, {"id": "13936005", "type": "test", "year": "2018", "stage": "2", "subject": "ros", "voivodeship": "mazowieckie", "school": "gim"}, {"id": "45393508", "type": "test", "year": "2018", "stage": "2", "subject": "his", "voivodeship": "mazowieckie", "school": "gim"}, {"id": "49886108", "type": "test", "year": "2018", "stage": "3", "subject": "mat", "voivodeship": "mazowieckie", "school": "gim"}, {"id": "18125555", "type": "test", "year": "2018", "stage": "3", "subject": "bio", "voivodeship": "mazowieckie", "school": "gim"}, {"id": "92849000", "type": "test", "year": "2018", "stage": "3", "subject": "fiz", "voivodeship": "mazowieckie", "school": "gim"}, {"id": "77656535", "type": "test", "year": "2018", "stage": "3", "subject": "geo", "voivodeship": "mazowieckie", "school": "gim"}, {"id": "50574011", "type": "test", "year": "2018", "stage": "3", "subject": "hip", "voivodeship": "mazowieckie", "school": "gim"}, {"id": "33297764", "type": "test", "year": "2018", "stage": "3", "subject": "fra", "voivodeship": "mazowieckie", "school": "gim"}, {"id": "63740200", "type": "test", "year": "2018", "stage": "3", "subject": "nie", "voivodeship": "mazowieckie", "school": "gim"}, {"id": "71481094", "type": "test", "year": "2018", "stage": "3", "subject": "ang", "voivodeship": "mazowieckie", "school": "gim"}, {"id": "66057058", "type": "test", "year": "2018", "stage": "3", "subject": "wos", "voivodeship": "mazowieckie", "school": "gim"}, {"id": "14445961", "type": "test", "year": "2018", "stage": "3", "subject": "che", "voivodeship": "mazowieckie", "school": "gim"}, {"id": "79439508", "type": "test", "year": "2018", "stage": "3", "subject": "pol", "voivodeship": "mazowieckie", "school": "gim"}, {"id": "49887825", "type": "test", "year": "2018", "stage": "3", "subject": "ros", "voivodeship": "mazowieckie", "school": "gim"}, {"id": "17172288", "type": "test", "year": "2018", "stage": "3", "subject": "his", "voivodeship": "mazowieckie", "school": "gim"}, {"id": "73888752", "type": "ans", "year": "2018", "stage": "1", "subject": "mat", "voivodeship": "mazowieckie", "school": "sp"}, {"id": "90949519", "type": "ans", "year": "2018", "stage": "1", "subject": "bio", "voivodeship": "mazowieckie", "school": "sp"}, {"id": "45422763", "type": "ans", "year": "2018", "stage": "1", "subject": "fiz", "voivodeship": "mazowieckie", "school": "sp"}, {"id": "71137331", "type": "ans", "year": "2018", "stage": "1", "subject": "geo", "voivodeship": "mazowieckie", "school": "sp"}, {"id": "13446722", "type": "ans", "year": "2018", "stage": "1", "subject": "hip", "voivodeship": "mazowieckie", "school": "sp"}, {"id": "90028448", "type": "ans", "year": "2018", "stage": "1", "subject": "fra", "voivodeship": "mazowieckie", "school": "sp"}, {"id": "98675994", "type": "ans", "year": "2018", "stage": "1", "subject": "nie", "voivodeship": "mazowieckie", "school": "sp"}, {"id": "16587903", "type": "ans", "year": "2018", "stage": "1", "subject": "ang", "voivodeship": "mazowieckie", "school": "sp"}, {"id": "49758105", "type": "ans", "year": "2018", "stage": "1", "subject": "wos", "voivodeship": "mazowieckie", "school": "sp"}, {"id": "53778119", "type": "ans", "year": "2018", "stage": "1", "subject": "che", "voivodeship": "mazowieckie", "school": "sp"}, {"id": "48526539", "type": "ans", "year": "2018", "stage": "1", "subject": "pol", "voivodeship": "mazowieckie", "school": "sp"}, {"id": "85497046", "type": "ans", "year": "2018", "stage": "1", "subject": "ros", "voivodeship": "mazowieckie", "school": "sp"}, {"id": "33436384", "type": "ans", "year": "2018", "stage": "1", "subject": "his", "voivodeship": "mazowieckie", "school": "sp"}, {"id": "20558431", "type": "ans", "year": "2018", "stage": "2", "subject": "mat", "voivodeship": "mazowieckie", "school": "sp"}, {"id": "40772858", "type": "ans", "year": "2018", "stage": "2", "subject": "bio", "voivodeship": "mazowieckie", "school": "sp"}, {"id": "13608006", "type": "ans", "year": "2018", "stage": "2", "subject": "fiz", "voivodeship": "mazowieckie", "school": "sp"}, {"id": "60110316", "type": "ans", "year": "2018", "stage": "2", "subject": "geo", "voivodeship": "mazowieckie", "school": "sp"}, {"id": "77084224", "type": "ans", "year": "2018", "stage": "2", "subject": "hip", "voivodeship": "mazowieckie", "school": "sp"}, {"id": "28858136", "type": "ans", "year": "2018", "stage": "2", "subject": "fra", "voivodeship": "mazowieckie", "school": "sp"}, {"id": "80524172", "type": "ans", "year": "2018", "stage": "2", "subject": "nie", "voivodeship": "mazowieckie", "school": "sp"}, {"id": "75349908", "type": "ans", "year": "2018", "stage": "2", "subject": "ang", "voivodeship": "mazowieckie", "school": "sp"}, {"id": "33942025", "type": "ans", "year": "2018", "stage": "2", "subject": "wos", "voivodeship": "mazowieckie", "school": "sp"}, {"id": "90160297", "type": "ans", "year": "2018", "stage": "2", "subject": "che", "voivodeship": "mazowieckie", "school": "sp"}, {"id": "14350729", "type": "ans", "year": "2018", "stage": "2", "subject": "pol", "voivodeship": "mazowieckie", "school": "sp"}, {"id": "12145070", "type": "ans", "year": "2018", "stage": "2", "subject": "ros", "voivodeship": "mazowieckie", "school": "sp"}, {"id": "69792105", "type": "ans", "year": "2018", "stage": "2", "subject": "his", "voivodeship": "mazowieckie", "school": "sp"}, {"id": "52201522", "type": "ans", "year": "2018", "stage": "3", "subject": "mat", "voivodeship": "mazowieckie", "school": "sp"}, {"id": "99187237", "type": "ans", "year": "2018", "stage": "3", "subject": "bio", "voivodeship": "mazowieckie", "school": "sp"}, {"id": "93136078", "type": "ans", "year": "2018", "stage": "3", "subject": "fiz", "voivodeship": "mazowieckie", "school": "sp"}, {"id": "66917891", "type": "ans", "year": "2018", "stage": "3", "subject": "geo", "voivodeship": "mazowieckie", "school": "sp"}, {"id": "46629787", "type": "ans", "year": "2018", "stage": "3", "subject": "hip", "voivodeship": "mazowieckie", "school": "sp"}, {"id": "50061305", "type": "ans", "year": "2018", "stage": "3", "subject": "fra", "voivodeship": "mazowieckie", "school": "sp"}, {"id": "11104801", "type": "ans", "year": "2018", "stage": "3", "subject": "nie", "voivodeship": "mazowieckie", "school": "sp"}, {"id": "38054374", "type": "ans", "year": "2018", "stage": "3", "subject": "ang", "voivodeship": "mazowieckie", "school": "sp"}, {"id": "16757961", "type": "ans", "year": "2018", "stage": "3", "subject": "wos", "voivodeship": "mazowieckie", "school": "sp"}, {"id": "69387562", "type": "ans", "year": "2018", "stage": "3", "subject": "che", "voivodeship": "mazowieckie", "school": "sp"}, {"id": "46843294", "type": "ans", "year": "2018", "stage": "3", "subject": "pol", "voivodeship": "mazowieckie", "school": "sp"}, {"id": "34967432", "type": "ans", "year": "2018", "stage": "3", "subject": "ros", "voivodeship": "mazowieckie", "school": "sp"}, {"id": "61174629", "type": "ans", "year": "2018", "stage": "3", "subject": "his", "voivodeship": "mazowieckie", "school": "sp"}, {"id": "22348444", "type": "ans", "year": "2018", "stage": "1", "subject": "mat", "voivodeship": "mazowieckie", "school": "gim"}, {"id": "48646722", "type": "ans", "year": "2018", "stage": "1", "subject": "bio", "voivodeship": "mazowieckie", "school": "gim"}, {"id": "38365151", "type": "ans", "year": "2018", "stage": "1", "subject": "fiz", "voivodeship": "mazowieckie", "school": "gim"}, {"id": "39523737", "type": "ans", "year": "2018", "stage": "1", "subject": "geo", "voivodeship": "mazowieckie", "school": "gim"}, {"id": "55318540", "type": "ans", "year": "2018", "stage": "1", "subject": "hip", "voivodeship": "mazowieckie", "school": "gim"}, {"id": "35578404", "type": "ans", "year": "2018", "stage": "1", "subject": "fra", "voivodeship": "mazowieckie", "school": "gim"}, {"id": "84475796", "type": "ans", "year": "2018", "stage": "1", "subject": "nie", "voivodeship": "mazowieckie", "school": "gim"}, {"id": "59353393", "type": "ans", "year": "2018", "stage": "1", "subject": "ang", "voivodeship": "mazowieckie", "school": "gim"}, {"id": "65449173", "type": "ans", "year": "2018", "stage": "1", "subject": "wos", "voivodeship": "mazowieckie", "school": "gim"}, {"id": "38850499", "type": "ans", "year": "2018", "stage": "1", "subject": "che", "voivodeship": "mazowieckie", "school": "gim"}, {"id": "58780870", "type": "ans", "year": "2018", "stage": "1", "subject": "pol", "voivodeship": "mazowieckie", "school": "gim"}, {"id": "65494253", "type": "ans", "year": "2018", "stage": "1", "subject": "ros", "voivodeship": "mazowieckie", "school": "gim"}, {"id": "88266962", "type": "ans", "year": "2018", "stage": "1", "subject": "his", "voivodeship": "mazowieckie", "school": "gim"}, {"id": "87119478", "type": "ans", "year": "2018", "stage": "2", "subject": "mat", "voivodeship": "mazowieckie", "school": "gim"}, {"id": "26494116", "type": "ans", "year": "2018", "stage": "2", "subject": "bio", "voivodeship": "mazowieckie", "school": "gim"}, {"id": "20011726", "type": "ans", "year": "2018", "stage": "2", "subject": "fiz", "voivodeship": "mazowieckie", "school": "gim"}, {"id": "88177287", "type": "ans", "year": "2018", "stage": "2", "subject": "geo", "voivodeship": "mazowieckie", "school": "gim"}, {"id": "54385639", "type": "ans", "year": "2018", "stage": "2", "subject": "hip", "voivodeship": "mazowieckie", "school": "gim"}, {"id": "32792610", "type": "ans", "year": "2018", "stage": "2", "subject": "fra", "voivodeship": "mazowieckie", "school": "gim"}, {"id": "73990107", "type": "ans", "year": "2018", "stage": "2", "subject": "nie", "voivodeship": "mazowieckie", "school": "gim"}, {"id": "39342263", "type": "ans", "year": "2018", "stage": "2", "subject": "ang", "voivodeship": "mazowieckie", "school": "gim"}, {"id": "53168944", "type": "ans", "year": "2018", "stage": "2", "subject": "wos", "voivodeship": "mazowieckie", "school": "gim"}, {"id": "76402505", "type": "ans", "year": "2018", "stage": "2", "subject": "che", "voivodeship": "mazowieckie", "school": "gim"}, {"id": "27345155", "type": "ans", "year": "2018", "stage": "2", "subject": "pol", "voivodeship": "mazowieckie", "school": "gim"}, {"id": "68387856", "type": "ans", "year": "2018", "stage": "2", "subject": "ros", "voivodeship": "mazowieckie", "school": "gim"}, {"id": "17437171", "type": "ans", "year": "2018", "stage": "2", "subject": "his", "voivodeship": "mazowieckie", "school": "gim"}, {"id": "89451755", "type": "ans", "year": "2018", "stage": "3", "subject": "mat", "voivodeship": "mazowieckie", "school": "gim"}, {"id": "67136653", "type": "ans", "year": "2018", "stage": "3", "subject": "bio", "voivodeship": "mazowieckie", "school": "gim"}, {"id": "37874894", "type": "ans", "year": "2018", "stage": "3", "subject": "fiz", "voivodeship": "mazowieckie", "school": "gim"}, {"id": "59110517", "type": "ans", "year": "2018", "stage": "3", "subject": "geo", "voivodeship": "mazowieckie", "school": "gim"}, {"id": "87035065", "type": "ans", "year": "2018", "stage": "3", "subject": "hip", "voivodeship": "mazowieckie", "school": "gim"}, {"id": "85839079", "type": "ans", "year": "2018", "stage": "3", "subject": "fra", "voivodeship": "mazowieckie", "school": "gim"}, {"id": "30413142", "type": "ans", "year": "2018", "stage": "3", "subject": "nie", "voivodeship": "mazowieckie", "school": "gim"}, {"id": "13936995", "type": "ans", "year": "2018", "stage": "3", "subject": "ang", "voivodeship": "mazowieckie", "school": "gim"}, {"id": "39374659", "type": "ans", "year": "2018", "stage": "3", "subject": "wos", "voivodeship": "mazowieckie", "school": "gim"}, {"id": "18434977", "type": "ans", "year": "2018", "stage": "3", "subject": "che", "voivodeship": "mazowieckie", "school": "gim"}, {"id": "52190081", "type": "ans", "year": "2018", "stage": "3", "subject": "pol", "voivodeship": "mazowieckie", "school": "gim"}, {"id": "69806400", "type": "ans", "year": "2018", "stage": "3", "subject": "ros", "voivodeship": "mazowieckie", "school": "gim"}, {"id": "75660874", "type": "ans", "year": "2018", "stage": "3", "subject": "his", "voivodeship": "mazowieckie", "school": "gim"}, {"id": "48236223", "type": "test", "year": "2017", "stage": "1", "subject": "mat", "voivodeship": "mazowieckie", "school": "gim"}, {"id": "99777944", "type": "test", "year": "2017", "stage": "1", "subject": "bio", "voivodeship": "mazowieckie", "school": "gim"}, {"id": "90518093", "type": "test", "year": "2017", "stage": "1", "subject": "fiz", "voivodeship": "mazowieckie", "school": "gim"}, {"id": "20590646", "type": "test", "year": "2017", "stage": "1", "subject": "geo", "voivodeship": "mazowieckie", "school": "gim"}, {"id": "63660455", "type": "test", "year": "2017", "stage": "1", "subject": "hip", "voivodeship": "mazowieckie", "school": "gim"}, {"id": "89702911", "type": "test", "year": "2017", "stage": "1", "subject": "fra", "voivodeship": "mazowieckie", "school": "gim"}, {"id": "55624339", "type": "test", "year": "2017", "stage": "1", "subject": "nie", "voivodeship": "mazowieckie", "school": "gim"}, {"id": "85333264", "type": "test", "year": "2017", "stage": "1", "subject": "ang", "voivodeship": "mazowieckie", "school": "gim"}, {"id": "63412543", "type": "test", "year": "2017", "stage": "1", "subject": "wos", "voivodeship": "mazowieckie", "school": "gim"}, {"id": "55075224", "type": "test", "year": "2017", "stage": "1", "subject": "che", "voivodeship": "mazowieckie", "school": "gim"}, {"id": "76216915", "type": "test", "year": "2017", "stage": "1", "subject": "pol", "voivodeship": "mazowieckie", "school": "gim"}, {"id": "85088731", "type": "test", "year": "2017", "stage": "1", "subject": "ros", "voivodeship": "mazowieckie", "school": "gim"}, {"id": "21208190", "type": "test", "year": "2017", "stage": "1", "subject": "his", "voivodeship": "mazowieckie", "school": "gim"}, {"id": "12960097", "type": "test", "year": "2017", "stage": "2", "subject": "mat", "voivodeship": "mazowieckie", "school": "gim"}, {"id": "70319715", "type": "test", "year": "2017", "stage": "2", "subject": "bio", "voivodeship": "mazowieckie", "school": "gim"}, {"id": "73045539", "type": "test", "year": "2017", "stage": "2", "subject": "fiz", "voivodeship": "mazowieckie", "school": "gim"}, {"id": "90504658", "type": "test", "year": "2017", "stage": "2", "subject": "geo", "voivodeship": "mazowieckie", "school": "gim"}, {"id": "15667126", "type": "test", "year": "2017", "stage": "2", "subject": "hip", "voivodeship": "mazowieckie", "school": "gim"}, {"id": "82111487", "type": "test", "year": "2017", "stage": "2", "subject": "fra", "voivodeship": "mazowieckie", "school": "gim"}, {"id": "79820496", "type": "test", "year": "2017", "stage": "2", "subject": "nie", "voivodeship": "mazowieckie", "school": "gim"}, {"id": "97513930", "type": "test", "year": "2017", "stage": "2", "subject": "ang", "voivodeship": "mazowieckie", "school": "gim"}, {"id": "73074881", "type": "test", "year": "2017", "stage": "2", "subject": "wos", "voivodeship": "mazowieckie", "school": "gim"}, {"id": "17453951", "type": "test", "year": "2017", "stage": "2", "subject": "che", "voivodeship": "mazowieckie", "school": "gim"}, {"id": "78820847", "type": "test", "year": "2017", "stage": "2", "subject": "pol", "voivodeship": "mazowieckie", "school": "gim"}, {"id": "10492047", "type": "test", "year": "2017", "stage": "2", "subject": "ros", "voivodeship": "mazowieckie", "school": "gim"}, {"id": "64416836", "type": "test", "year": "2017", "stage": "2", "subject": "his", "voivodeship": "mazowieckie", "school": "gim"}, {"id": "24084791", "type": "test", "year": "2017", "stage": "3", "subject": "mat", "voivodeship": "mazowieckie", "school": "gim"}, {"id": "51802503", "type": "test", "year": "2017", "stage": "3", "subject": "bio", "voivodeship": "mazowieckie", "school": "gim"}, {"id": "23449596", "type": "test", "year": "2017", "stage": "3", "subject": "fiz", "voivodeship": "mazowieckie", "school": "gim"}, {"id": "37407363", "type": "test", "year": "2017", "stage": "3", "subject": "geo", "voivodeship": "mazowieckie", "school": "gim"}, {"id": "36781299", "type": "test", "year": "2017", "stage": "3", "subject": "hip", "voivodeship": "mazowieckie", "school": "gim"}, {"id": "72357247", "type": "test", "year": "2017", "stage": "3", "subject": "fra", "voivodeship": "mazowieckie", "school": "gim"}, {"id": "91110281", "type": "test", "year": "2017", "stage": "3", "subject": "nie", "voivodeship": "mazowieckie", "school": "gim"}, {"id": "30054399", "type": "test", "year": "2017", "stage": "3", "subject": "ang", "voivodeship": "mazowieckie", "school": "gim"}, {"id": "97876258", "type": "test", "year": "2017", "stage": "3", "subject": "wos", "voivodeship": "mazowieckie", "school": "gim"}, {"id": "12068051", "type": "test", "year": "2017", "stage": "3", "subject": "che", "voivodeship": "mazowieckie", "school": "gim"}, {"id": "96796718", "type": "test", "year": "2017", "stage": "3", "subject": "pol", "voivodeship": "mazowieckie", "school": "gim"}, {"id": "14818916", "type": "test", "year": "2017", "stage": "3", "subject": "ros", "voivodeship": "mazowieckie", "school": "gim"}, {"id": "22593290", "type": "test", "year": "2017", "stage": "3", "subject": "his", "voivodeship": "mazowieckie", "school": "gim"}, {"id": "43005396", "type": "ans", "year": "2017", "stage": "1", "subject": "mat", "voivodeship": "mazowieckie", "school": "gim"}, {"id": "69210048", "type": "ans", "year": "2017", "stage": "1", "subject": "bio", "voivodeship": "mazowieckie", "school": "gim"}, {"id": "57206597", "type": "ans", "year": "2017", "stage": "1", "subject": "fiz", "voivodeship": "mazowieckie", "school": "gim"}, {"id": "77317003", "type": "ans", "year": "2017", "stage": "1", "subject": "geo", "voivodeship": "mazowieckie", "school": "gim"}, {"id": "72226125", "type": "ans", "year": "2017", "stage": "1", "subject": "hip", "voivodeship": "mazowieckie", "school": "gim"}, {"id": "87663605", "type": "ans", "year": "2017", "stage": "1", "subject": "fra", "voivodeship": "mazowieckie", "school": "gim"}, {"id": "16861038", "type": "ans", "year": "2017", "stage": "1", "subject": "nie", "voivodeship": "mazowieckie", "school": "gim"}, {"id": "98227531", "type": "ans", "year": "2017", "stage": "1", "subject": "ang", "voivodeship": "mazowieckie", "school": "gim"}, {"id": "71885610", "type": "ans", "year": "2017", "stage": "1", "subject": "wos", "voivodeship": "mazowieckie", "school": "gim"}, {"id": "71022906", "type": "ans", "year": "2017", "stage": "1", "subject": "che", "voivodeship": "mazowieckie", "school": "gim"}, {"id": "82452375", "type": "ans", "year": "2017", "stage": "1", "subject": "pol", "voivodeship": "mazowieckie", "school": "gim"}, {"id": "42542390", "type": "ans", "year": "2017", "stage": "1", "subject": "ros", "voivodeship": "mazowieckie", "school": "gim"}, {"id": "73078144", "type": "ans", "year": "2017", "stage": "1", "subject": "his", "voivodeship": "mazowieckie", "school": "gim"}, {"id": "89443176", "type": "ans", "year": "2017", "stage": "2", "subject": "mat", "voivodeship": "mazowieckie", "school": "gim"}, {"id": "89596148", "type": "ans", "year": "2017", "stage": "2", "subject": "bio", "voivodeship": "mazowieckie", "school": "gim"}, {"id": "12708942", "type": "ans", "year": "2017", "stage": "2", "subject": "fiz", "voivodeship": "mazowieckie", "school": "gim"}, {"id": "87507569", "type": "ans", "year": "2017", "stage": "2", "subject": "geo", "voivodeship": "mazowieckie", "school": "gim"}, {"id": "22447719", "type": "ans", "year": "2017", "stage": "2", "subject": "hip", "voivodeship": "mazowieckie", "school": "gim"}, {"id": "74225176", "type": "ans", "year": "2017", "stage": "2", "subject": "fra", "voivodeship": "mazowieckie", "school": "gim"}, {"id": "53776101", "type": "ans", "year": "2017", "stage": "2", "subject": "nie", "voivodeship": "mazowieckie", "school": "gim"}, {"id": "67080948", "type": "ans", "year": "2017", "stage": "2", "subject": "ang", "voivodeship": "mazowieckie", "school": "gim"}, {"id": "56036299", "type": "ans", "year": "2017", "stage": "2", "subject": "wos", "voivodeship": "mazowieckie", "school": "gim"}, {"id": "76258856", "type": "ans", "year": "2017", "stage": "2", "subject": "che", "voivodeship": "mazowieckie", "school": "gim"}, {"id": "45022029", "type": "ans", "year": "2017", "stage": "2", "subject": "pol", "voivodeship": "mazowieckie", "school": "gim"}, {"id": "88490952", "type": "ans", "year": "2017", "stage": "2", "subject": "ros", "voivodeship": "mazowieckie", "school": "gim"}, {"id": "38860322", "type": "ans", "year": "2017", "stage": "2", "subject": "his", "voivodeship": "mazowieckie", "school": "gim"}, {"id": "13617201", "type": "ans", "year": "2017", "stage": "3", "subject": "mat", "voivodeship": "mazowieckie", "school": "gim"}, {"id": "47709432", "type": "ans", "year": "2017", "stage": "3", "subject": "bio", "voivodeship": "mazowieckie", "school": "gim"}, {"id": "34190349", "type": "ans", "year": "2017", "stage": "3", "subject": "fiz", "voivodeship": "mazowieckie", "school": "gim"}, {"id": "34930449", "type": "ans", "year": "2017", "stage": "3", "subject": "geo", "voivodeship": "mazowieckie", "school": "gim"}, {"id": "53610870", "type": "ans", "year": "2017", "stage": "3", "subject": "hip", "voivodeship": "mazowieckie", "school": "gim"}, {"id": "53788323", "type": "ans", "year": "2017", "stage": "3", "subject": "fra", "voivodeship": "mazowieckie", "school": "gim"}, {"id": "18674167", "type": "ans", "year": "2017", "stage": "3", "subject": "nie", "voivodeship": "mazowieckie", "school": "gim"}, {"id": "93402742", "type": "ans", "year": "2017", "stage": "3", "subject": "ang", "voivodeship": "mazowieckie", "school": "gim"}, {"id": "17718116", "type": "ans", "year": "2017", "stage": "3", "subject": "wos", "voivodeship": "mazowieckie", "school": "gim"}, {"id": "46925311", "type": "ans", "year": "2017", "stage": "3", "subject": "che", "voivodeship": "mazowieckie", "school": "gim"}, {"id": "34547952", "type": "ans", "year": "2017", "stage": "3", "subject": "pol", "voivodeship": "mazowieckie", "school": "gim"}, {"id": "89089170", "type": "ans", "year": "2017", "stage": "3", "subject": "ros", "voivodeship": "mazowieckie", "school": "gim"}, {"id": "45610246", "type": "ans", "year": "2017", "stage": "3", "subject": "his", "voivodeship": "mazowieckie", "school": "gim"}, {"id": "89614051", "type": "test", "year": "2017", "stage": "1", "subject": "pol", "voivodeship": "mazowieckie", "school": "sp"}, {"id": "55945199", "type": "test", "year": "2017", "stage": "2", "subject": "pol", "voivodeship": "mazowieckie", "school": "sp"}, {"id": "58444112", "type": "test", "year": "2017", "stage": "3", "subject": "pol", "voivodeship": "mazowieckie", "school": "sp"}, {"id": "50089203", "type": "ans", "year": "2017", "stage": "1", "subject": "pol", "voivodeship": "mazowieckie", "school": "sp"}, {"id": "27102675", "type": "ans", "year": "2017", "stage": "2", "subject": "pol", "voivodeship": "mazowieckie", "school": "sp"}, {"id": "71922311", "type": "ans", "year": "2017", "stage": "3", "subject": "pol", "voivodeship": "mazowieckie", "school": "sp"}, {"id": "27152355", "type": "test", "year": "2017", "stage": "1", "subject": "mat", "voivodeship": "mazowieckie", "school": "sp"}, {"id": "20788559", "type": "test", "year": "2017", "stage": "2", "subject": "mat", "voivodeship": "mazowieckie", "school": "sp"}, {"id": "99029003", "type": "test", "year": "2017", "stage": "3", "subject": "mat", "voivodeship": "mazowieckie", "school": "sp"}, {"id": "25327872", "type": "ans", "year": "2017", "stage": "1", "subject": "mat", "voivodeship": "mazowieckie", "school": "sp"}, {"id": "33568344", "type": "ans", "year": "2017", "stage": "2", "subject": "mat", "voivodeship": "mazowieckie", "school": "sp"}, {"id": "22134608", "type": "ans", "year": "2017", "stage": "3", "subject": "mat", "voivodeship": "mazowieckie", "school": "sp"}, {"id": "18270217", "type": "test", "year": "2018", "stage": "1", "subject": "kwm", "voivodeship": "mazowieckie", "school": "sp"}, {"id": "92584067", "type": "test", "year": "2018", "stage": "2", "subject": "kwm", "voivodeship": "mazowieckie", "school": "sp"}, {"id": "22273682", "type": "test", "year": "2018", "stage": "3", "subject": "kwm", "voivodeship": "mazowieckie", "school": "sp"}, {"id": "25251614", "type": "ans", "year": "2018", "stage": "3", "subject": "kwm", "voivodeship": "mazowieckie", "school": "sp"}, {"id": "77152184", "type": "ans", "year": "2018", "stage": "2", "subject": "kwm", "voivodeship": "mazowieckie", "school": "sp"}, {"id": "19821506", "type": "ans", "year": "2018", "stage": "1", "subject": "kwm", "voivodeship": "mazowieckie", "school": "sp"}, {"id": "33563715", "type": "test", "year": "2019", "stage": "1", "subject": "hip", "voivodeship": "mazowieckie", "school": "sp"}, {"id": "46145552", "type": "ans", "year": "2019", "stage": "1", "subject": "hip", "voivodeship": "mazowieckie", "school": "sp"}, {"id": "92446864", "type": "test", "year": "2019", "stage": "1", "subject": "fra", "voivodeship": "mazowieckie", "school": "sp"}, {"id": "59884376", "type": "ans", "year": "2019", "stage": "1", "subject": "fra", "voivodeship": "mazowieckie", "school": "sp"}, {"id": "90423108", "type": "ans", "year": "2019", "stage": "1", "subject": "nie", "voivodeship": "mazowieckie", "school": "sp"}, {"id": "57323162", "type": "test", "year": "2019", "stage": "1", "subject": "nie", "voivodeship": "mazowieckie", "school": "sp"}, {"id": "72717855", "type": "test", "year": "2019", "stage": "1", "subject": "che", "voivodeship": "mazowieckie", "school": "sp"}, {"id": "36021811", "type": "test", "year": "2019", "stage": "1", "subject": "pol", "voivodeship": "mazowieckie", "school": "sp"}, {"id": "69942644", "type": "ans", "year": "2019", "stage": "1", "subject": "che", "voivodeship": "mazowieckie", "school": "sp"}, {"id": "30309423", "type": "ans", "year": "2019", "stage": "1", "subject": "pol", "voivodeship": "mazowieckie", "school": "sp"}, {"id": "27717115", "type": "ans", "year": "2019", "stage": "1", "subject": "ang", "voivodeship": "mazowieckie", "school": "sp"}, {"id": "24094182", "type": "test", "year": "2019", "stage": "1", "subject": "ang", "voivodeship": "mazowieckie", "school": "sp"}, {"id": "60828342", "type": "test", "year": "2019", "stage": "1", "subject": "his", "voivodeship": "mazowieckie", "school": "sp"}, {"id": "16064354", "type": "ans", "year": "2019", "stage": "1", "subject": "his", "voivodeship": "mazowieckie", "school": "sp"}, {"id": "92958348", "type": "ans", "year": "2019", "stage": "1", "subject": "bio", "voivodeship": "mazowieckie", "school": "sp"}, {"id": "53339246", "type": "ans", "year": "2019", "stage": "1", "subject": "mat", "voivodeship": "mazowieckie", "school": "sp"}, {"id": "63594652", "type": "test", "year": "2019", "stage": "1", "subject": "bio", "voivodeship": "mazowieckie", "school": "sp"}, {"id": "49106965", "type": "test", "year": "2019", "stage": "1", "subject": "mat", "voivodeship": "mazowieckie", "school": "sp"}, {"id": "85164754", "type": "test", "year": "2019", "stage": "1", "subject": "wos", "voivodeship": "mazowieckie", "school": "sp"}, {"id": "43048946", "type": "test", "year": "2019", "stage": "1", "subject": "ros", "voivodeship": "mazowieckie", "school": "sp"}, {"id": "45136452", "type": "ans", "year": "2019", "stage": "1", "subject": "wos", "voivodeship": "mazowieckie", "school": "sp"}, {"id": "93471099", "type": "ans", "year": "2019", "stage": "1", "subject": "ros", "voivodeship": "mazowieckie", "school": "sp"}, {"id": "26747331", "type": "ans", "year": "2019", "stage": "1", "subject": "geo", "voivodeship": "mazowieckie", "school": "sp"}, {"id": "50190455", "type": "ans", "year": "2019", "stage": "1", "subject": "fiz", "voivodeship": "mazowieckie", "school": "sp"}, {"id": "12366381", "type": "test", "year": "2019", "stage": "1", "subject": "fiz", "voivodeship": "mazowieckie", "school": "sp"}, {"id": "97115439", "type": "test", "year": "2019", "stage": "1", "subject": "geo", "voivodeship": "mazowieckie", "school": "sp"}, {"id": "82022592", "type": "ans", "year": "2019", "stage": "2", "subject": "fra", "voivodeship": "mazowieckie", "school": "sp"}, {"id": "94895294", "type": "ans", "year": "2019", "stage": "2", "subject": "hip", "voivodeship": "mazowieckie", "school": "sp"}, {"id": "10199305", "type": "test", "year": "2019", "stage": "2", "subject": "hip", "voivodeship": "mazowieckie", "school": "sp"}, {"id": "54339203", "type": "test", "year": "2019", "stage": "2", "subject": "fra", "voivodeship": "mazowieckie", "school": "sp"}, {"id": "25357758", "type": "test", "year": "2019", "stage": "2", "subject": "nie", "voivodeship": "mazowieckie", "school": "sp"}, {"id": "93336362", "type": "test", "year": "2019", "stage": "2", "subject": "pol", "voivodeship": "mazowieckie", "school": "sp"}, {"id": "15153973", "type": "ans", "year": "2019", "stage": "2", "subject": "nie", "voivodeship": "mazowieckie", "school": "sp"}, {"id": "71487917", "type": "ans", "year": "2019", "stage": "2", "subject": "pol", "voivodeship": "mazowieckie", "school": "sp"}, {"id": "79998324", "type": "ans", "year": "2019", "stage": "2", "subject": "che", "voivodeship": "mazowieckie", "school": "sp"}, {"id": "24229021", "type": "test", "year": "2019", "stage": "2", "subject": "che", "voivodeship": "mazowieckie", "school": "sp"}, {"id": "70343623", "type": "test", "year": "2019", "stage": "2", "subject": "ang", "voivodeship": "mazowieckie", "school": "sp"}, {"id": "91851266", "type": "ans", "year": "2019", "stage": "2", "subject": "ang", "voivodeship": "mazowieckie", "school": "sp"}, {"id": "46037113", "type": "ans", "year": "2019", "stage": "2", "subject": "his", "voivodeship": "mazowieckie", "school": "sp"}, {"id": "90019978", "type": "test", "year": "2019", "stage": "2", "subject": "his", "voivodeship": "mazowieckie", "school": "sp"}, {"id": "48440127", "type": "test", "year": "2019", "stage": "2", "subject": "bio", "voivodeship": "mazowieckie", "school": "sp"}, {"id": "73562655", "type": "ans", "year": "2019", "stage": "2", "subject": "bio", "voivodeship": "mazowieckie", "school": "sp"}, {"id": "60745767", "type": "ans", "year": "2019", "stage": "2", "subject": "mat", "voivodeship": "mazowieckie", "school": "sp"}, {"id": "40719980", "type": "test", "year": "2019", "stage": "2", "subject": "mat", "voivodeship": "mazowieckie", "school": "sp"}, {"id": "25149663", "type": "test", "year": "2019", "stage": "2", "subject": "wos", "voivodeship": "mazowieckie", "school": "sp"}, {"id": "71355551", "type": "ans", "year": "2019", "stage": "2", "subject": "wos", "voivodeship": "mazowieckie", "school": "sp"}, {"id": "60754316", "type": "ans", "year": "2019", "stage": "2", "subject": "geo", "voivodeship": "mazowieckie", "school": "sp"}, {"id": "34556452", "type": "test", "year": "2019", "stage": "2", "subject": "geo", "voivodeship": "mazowieckie", "school": "sp"}, {"id": "20430944", "type": "test", "year": "2019", "stage": "2", "subject": "ros", "voivodeship": "mazowieckie", "school": "sp"}, {"id": "29234986", "type": "ans", "year": "2019", "stage": "2", "subject": "ros", "voivodeship": "mazowieckie", "school": "sp"}, {"id": "24161157", "type": "ans", "year": "2019", "stage": "2", "subject": "fiz", "voivodeship": "mazowieckie", "school": "sp"}, {"id": "64661367", "type": "test", "year": "2019", "stage": "2", "subject": "fiz", "voivodeship": "mazowieckie", "school": "sp"}, {"id": "65298808", "type": "test", "year": "2019", "stage": "3", "subject": "hip", "voivodeship": "mazowieckie", "school": "sp"}, {"id": "80033054", "type": "test", "year": "2019", "stage": "3", "subject": "fra", "voivodeship": "mazowieckie", "school": "sp"}, {"id": "39031637", "type": "ans", "year": "2019", "stage": "3", "subject": "hip", "voivodeship": "mazowieckie", "school": "sp"}, {"id": "81748823", "type": "ans", "year": "2019", "stage": "3", "subject": "fra", "voivodeship": "mazowieckie", "school": "sp"}, {"id": "63391026", "type": "ans", "year": "2019", "stage": "3", "subject": "nie", "voivodeship": "mazowieckie", "school": "sp"}, {"id": "37836385", "type": "test", "year": "2019", "stage": "3", "subject": "nie", "voivodeship": "mazowieckie", "school": "sp"}, {"id": "78477440", "type": "ans", "year": "2019", "stage": "3", "subject": "pol", "voivodeship": "mazowieckie", "school": "sp"}, {"id": "47989975", "type": "ans", "year": "2019", "stage": "3", "subject": "che", "voivodeship": "mazowieckie", "school": "sp"}, {"id": "93164683", "type": "test", "year": "2019", "stage": "3", "subject": "che", "voivodeship": "mazowieckie", "school": "sp"}, {"id": "45139347", "type": "test", "year": "2019", "stage": "3", "subject": "pol", "voivodeship": "mazowieckie", "school": "sp"}, {"id": "85917371", "type": "test", "year": "2019", "stage": "3", "subject": "ang", "voivodeship": "mazowieckie", "school": "sp"}, {"id": "15295968", "type": "ans", "year": "2019", "stage": "3", "subject": "ang", "voivodeship": "mazowieckie", "school": "sp"}, {"id": "83371240", "type": "ans", "year": "2019", "stage": "3", "subject": "his", "voivodeship": "mazowieckie", "school": "sp"}, {"id": "24610437", "type": "test", "year": "2019", "stage": "3", "subject": "his", "voivodeship": "mazowieckie", "school": "sp"}, {"id": "33033086", "type": "test", "year": "2019", "stage": "3", "subject": "bio", "voivodeship": "mazowieckie", "school": "sp"}, {"id": "66824947", "type": "ans", "year": "2019", "stage": "3", "subject": "bio", "voivodeship": "mazowieckie", "school": "sp"}, {"id": "99984520", "type": "ans", "year": "2019", "stage": "3", "subject": "mat", "voivodeship": "mazowieckie", "school": "sp"}, {"id": "67813801", "type": "test", "year": "2019", "stage": "3", "subject": "mat", "voivodeship": "mazowieckie", "school": "sp"}, {"id": "35031018", "type": "test", "year": "2019", "stage": "3", "subject": "wos", "voivodeship": "mazowieckie", "school": "sp"}, {"id": "50140392", "type": "ans", "year": "2019", "stage": "3", "subject": "wos", "voivodeship": "mazowieckie", "school": "sp"}, {"id": "61416895", "type": "ans", "year": "2019", "stage": "3", "subject": "ros", "voivodeship": "mazowieckie", "school": "sp"}, {"id": "94193695", "type": "test", "year": "2019", "stage": "3", "subject": "ros", "voivodeship": "mazowieckie", "school": "sp"}, {"id": "48992803", "type": "test", "year": "2019", "stage": "3", "subject": "geo", "voivodeship": "mazowieckie", "school": "sp"}, {"id": "42240157", "type": "test", "year": "2019", "stage": "3", "subject": "fiz", "voivodeship": "mazowieckie", "school": "sp"}, {"id": "73043551", "type": "ans", "year": "2019", "stage": "3", "subject": "fiz", "voivodeship": "mazowieckie", "school": "sp"}, {"id": "63362375", "type": "ans", "year": "2019", "stage": "3", "subject": "geo", "voivodeship": "mazowieckie", "school": "sp"}, {"id": "80146315", "type": "ans", "year": "2019", "stage": "1", "subject": "kwm", "voivodeship": "mazowieckie", "school": "sp"}, {"id": "72893849", "type": "test", "year": "2019", "stage": "1", "subject": "kwm", "voivodeship": "mazowieckie", "school": "sp"}, {"id": "74244698", "type": "ans", "year": "2019", "stage": "1", "subject": "kwm", "voivodeship": "mazowieckie", "school": "sp"}, {"id": "78093293", "type": "ans", "year": "2020", "stage": "1", "subject": "pol", "voivodeship": "mazowieckie", "school": "sp"}, {"id": "54856061", "type": "ans", "year": "2020", "stage": "1", "subject": "nie", "voivodeship": "mazowieckie", "school": "sp"}, {"id": "19380202", "type": "ans", "year": "2020", "stage": "1", "subject": "fra", "voivodeship": "mazowieckie", "school": "sp"}, {"id": "56358877", "type": "test", "year": "2020", "stage": "1", "subject": "pol", "voivodeship": "mazowieckie", "school": "sp"}, {"id": "40331921", "type": "test", "year": "2020", "stage": "1", "subject": "fra", "voivodeship": "mazowieckie", "school": "sp"}, {"id": "81402244", "type": "test", "year": "2020", "stage": "1", "subject": "nie", "voivodeship": "mazowieckie", "school": "sp"}, {"id": "13697321", "type": "test", "year": "2020", "stage": "1", "subject": "mat", "voivodeship": "mazowieckie", "school": "sp"}, {"id": "16254243", "type": "test", "year": "2020", "stage": "1", "subject": "hip", "voivodeship": "mazowieckie", "school": "sp"}, {"id": "69184464", "type": "test", "year": "2020", "stage": "1", "subject": "ros", "voivodeship": "mazowieckie", "school": "sp"}, {"id": "88020168", "type": "ans", "year": "2020", "stage": "1", "subject": "mat", "voivodeship": "mazowieckie", "school": "sp"}, {"id": "98935353", "type": "ans", "year": "2020", "stage": "1", "subject": "ros", "voivodeship": "mazowieckie", "school": "sp"}, {"id": "66358002", "type": "ans", "year": "2020", "stage": "1", "subject": "hip", "voivodeship": "mazowieckie", "school": "sp"}, {"id": "64856297", "type": "ans", "year": "2020", "stage": "1", "subject": "ang", "voivodeship": "mazowieckie", "school": "sp"}, {"id": "45222482", "type": "test", "year": "2020", "stage": "1", "subject": "ang", "voivodeship": "mazowieckie", "school": "sp"}, {"id": "17462540", "type": "test", "year": "2020", "stage": "1", "subject": "fiz", "voivodeship": "mazowieckie", "school": "sp"}, {"id": "40822460", "type": "test", "year": "2020", "stage": "1", "subject": "his", "voivodeship": "mazowieckie", "school": "sp"}, {"id": "84199435", "type": "ans", "year": "2020", "stage": "1", "subject": "fiz", "voivodeship": "mazowieckie", "school": "sp"}, {"id": "13946861", "type": "ans", "year": "2020", "stage": "1", "subject": "his", "voivodeship": "mazowieckie", "school": "sp"}, {"id": "12424870", "type": "ans", "year": "2020", "stage": "1", "subject": "bio", "voivodeship": "mazowieckie", "school": "sp"}, {"id": "76639772", "type": "ans", "year": "2020", "stage": "1", "subject": "wos", "voivodeship": "mazowieckie", "school": "sp"}, {"id": "69109668", "type": "test", "year": "2020", "stage": "1", "subject": "bio", "voivodeship": "mazowieckie", "school": "sp"}, {"id": "78885873", "type": "test", "year": "2020", "stage": "1", "subject": "wos", "voivodeship": "mazowieckie", "school": "sp"}, {"id": "77498574", "type": "test", "year": "2020", "stage": "1", "subject": "geo", "voivodeship": "mazowieckie", "school": "sp"}, {"id": "85478865", "type": "test", "year": "2020", "stage": "1", "subject": "che", "voivodeship": "mazowieckie", "school": "sp"}, {"id": "43031630", "type": "ans", "year": "2020", "stage": "1", "subject": "che", "voivodeship": "mazowieckie", "school": "sp"}, {"id": "35464265", "type": "ans", "year": "2020", "stage": "1", "subject": "geo", "voivodeship": "mazowieckie", "school": "sp"}, {"id": "43920480", "type": "test", "year": "2020", "stage": "2", "subject": "pol", "voivodeship": "mazowieckie", "school": "sp"}, {"id": "42260831", "type": "ans", "year": "2020", "stage": "2", "subject": "pol", "voivodeship": "mazowieckie", "school": "sp"}, {"id": "56530289", "type": "ans", "year": "2020", "stage": "2", "subject": "mat", "voivodeship": "mazowieckie", "school": "sp"}, {"id": "11027033", "type": "test", "year": "2020", "stage": "2", "subject": "mat", "voivodeship": "mazowieckie", "school": "sp"}, {"id": "60548141", "type": "test", "year": "2020", "stage": "2", "subject": "nie", "voivodeship": "mazowieckie", "school": "sp"}, {"id": "90201803", "type": "test", "year": "2020", "stage": "2", "subject": "fra", "voivodeship": "mazowieckie", "school": "sp"}, {"id": "49601865", "type": "ans", "year": "2020", "stage": "2", "subject": "nie", "voivodeship": "mazowieckie", "school": "sp"}, {"id": "58507510", "type": "ans", "year": "2020", "stage": "2", "subject": "fra", "voivodeship": "mazowieckie", "school": "sp"}, {"id": "51650648", "type": "ans", "year": "2020", "stage": "2", "subject": "ros", "voivodeship": "mazowieckie", "school": "sp"}, {"id": "33461200", "type": "ans", "year": "2020", "stage": "2", "subject": "hip", "voivodeship": "mazowieckie", "school": "sp"}, {"id": "97583743", "type": "test", "year": "2020", "stage": "2", "subject": "ros", "voivodeship": "mazowieckie", "school": "sp"}, {"id": "79883219", "type": "test", "year": "2020", "stage": "2", "subject": "hip", "voivodeship": "mazowieckie", "school": "sp"}, {"id": "47927313", "type": "test", "year": "2020", "stage": "2", "subject": "ang", "voivodeship": "mazowieckie", "school": "sp"}, {"id": "82558469", "type": "ans", "year": "2020", "stage": "2", "subject": "ang", "voivodeship": "mazowieckie", "school": "sp"}, {"id": "70351154", "type": "ans", "year": "2020", "stage": "2", "subject": "fiz", "voivodeship": "mazowieckie", "school": "sp"}, {"id": "16860982", "type": "ans", "year": "2020", "stage": "2", "subject": "his", "voivodeship": "mazowieckie", "school": "sp"}, {"id": "25020726", "type": "test", "year": "2020", "stage": "2", "subject": "his", "voivodeship": "mazowieckie", "school": "sp"}, {"id": "75765305", "type": "test", "year": "2020", "stage": "2", "subject": "fiz", "voivodeship": "mazowieckie", "school": "sp"}, {"id": "33992538", "type": "test", "year": "2020", "stage": "2", "subject": "geo", "voivodeship": "mazowieckie", "school": "sp"}, {"id": "30365456", "type": "ans", "year": "2020", "stage": "2", "subject": "geo", "voivodeship": "mazowieckie", "school": "sp"}, {"id": "48247131", "type": "ans", "year": "2020", "stage": "2", "subject": "che", "voivodeship": "mazowieckie", "school": "sp"}, {"id": "54926005", "type": "test", "year": "2020", "stage": "2", "subject": "che", "voivodeship": "mazowieckie", "school": "sp"}, {"id": "34634918", "type": "ans", "year": "2020", "stage": "2", "subject": "wos", "voivodeship": "mazowieckie", "school": "sp"}, {"id": "70416132", "type": "test", "year": "2020", "stage": "2", "subject": "wos", "voivodeship": "mazowieckie", "school": "sp"}, {"id": "51522232", "type": "test", "year": "2020", "stage": "2", "subject": "bio", "voivodeship": "mazowieckie", "school": "sp"}, {"id": "90988899", "type": "ans", "year": "2020", "stage": "2", "subject": "bio", "voivodeship": "mazowieckie", "school": "sp"}, {"id": "42207847", "type": "test", "year": "2020", "stage": "1", "subject": "kwm", "voivodeship": "mazowieckie", "school": "sp"}, {"id": "15283306", "type": "ans", "year": "2020", "stage": "1", "subject": "kwm", "voivodeship": "mazowieckie", "school": "sp"}, {"id": "92426007", "type": "ans", "year": "2020", "stage": "3", "subject": "pol", "voivodeship": "mazowieckie", "school": "sp"}, {"id": "52167490", "type": "test", "year": "2020", "stage": "3", "subject": "pol", "voivodeship": "mazowieckie", "school": "sp"}, {"id": "23318128", "type": "ans", "year": "2020", "stage": "3", "subject": "mat", "voivodeship": "mazowieckie", "school": "sp"}, {"id": "99863967", "type": "test", "year": "2020", "stage": "3", "subject": "mat", "voivodeship": "mazowieckie", "school": "sp"}, {"id": "23959312", "type": "test", "year": "2020", "stage": "3", "subject": "nie", "voivodeship": "mazowieckie", "school": "sp"}, {"id": "38528327", "type": "ans", "year": "2020", "stage": "3", "subject": "nie", "voivodeship": "mazowieckie", "school": "sp"}, {"id": "36554818", "type": "test", "year": "2020", "stage": "3", "subject": "fra", "voivodeship": "mazowieckie", "school": "sp"}, {"id": "93067870", "type": "ans", "year": "2020", "stage": "3", "subject": "fra", "voivodeship": "mazowieckie", "school": "sp"}, {"id": "36157714", "type": "ans", "year": "2020", "stage": "3", "subject": "ros", "voivodeship": "mazowieckie", "school": "sp"}, {"id": "74281156", "type": "test", "year": "2020", "stage": "3", "subject": "ros", "voivodeship": "mazowieckie", "school": "sp"}, {"id": "39284293", "type": "test", "year": "2020", "stage": "3", "subject": "ang", "voivodeship": "mazowieckie", "school": "sp"}, {"id": "52170510", "type": "ans", "year": "2020", "stage": "3", "subject": "ang", "voivodeship": "mazowieckie", "school": "sp"}, {"id": "34452563", "type": "ans", "year": "2020", "stage": "3", "subject": "hip", "voivodeship": "mazowieckie", "school": "sp"}, {"id": "41635776", "type": "test", "year": "2020", "stage": "3", "subject": "hip", "voivodeship": "mazowieckie", "school": "sp"}, {"id": "74104107", "type": "ans", "year": "2020", "stage": "2", "subject": "kwm", "voivodeship": "mazowieckie", "school": "sp"}, {"id": "29316401", "type": "test", "year": "2020", "stage": "2", "subject": "kwm", "voivodeship": "mazowieckie", "school": "sp"}, {"id": "47308293", "type": "test", "year": "2020", "stage": "3", "subject": "fiz", "voivodeship": "mazowieckie", "school": "sp"}, {"id": "63307531", "type": "ans", "year": "2020", "stage": "3", "subject": "fiz", "voivodeship": "mazowieckie", "school": "sp"}, {"id": "44025688", "type": "test", "year": "2020", "stage": "3", "subject": "his", "voivodeship": "mazowieckie", "school": "sp"}, {"id": "16818123", "type": "ans", "year": "2020", "stage": "3", "subject": "his", "voivodeship": "mazowieckie", "school": "sp"}, {"id": "92454890", "type": "test", "year": "2020", "stage": "3", "subject": "che", "voivodeship": "mazowieckie", "school": "sp"}, {"id": "54977531", "type": "ans", "year": "2020", "stage": "3", "subject": "che", "voivodeship": "mazowieckie", "school": "sp"}, {"id": "11557499", "type": "test", "year": "2020", "stage": "3", "subject": "geo", "voivodeship": "mazowieckie", "school": "sp"}, {"id": "38418572", "type": "ans", "year": "2020", "stage": "3", "subject": "geo", "voivodeship": "mazowieckie", "school": "sp"}, {"id": "22982000", "type": "test", "year": "2020", "stage": "3", "subject": "wos", "voivodeship": "mazowieckie", "school": "sp"}, {"id": "97632359", "type": "test", "year": "2020", "stage": "3", "subject": "bio", "voivodeship": "mazowieckie", "school": "sp"}, {"id": "34558107", "type": "ans", "year": "2020", "stage": "3", "subject": "wos", "voivodeship": "mazowieckie", "school": "sp"}, {"id": "43684746", "type": "ans", "year": "2020", "stage": "3", "subject": "bio", "voivodeship": "mazowieckie", "school": "sp"}, {"id": "33071767", "type": "test", "year": "2020", "stage": "3", "subject": "kwm", "voivodeship": "mazowieckie", "school": "sp"}, {"id": "47893550", "type": "ans", "year": "2020", "stage": "3", "subject": "kwm", "voivodeship": "mazowieckie", "school": "sp"}, {"id": "31091131", "type": "test", "year": "2021", "stage": "1", "subject": "mat", "voivodeship": "mazowieckie", "school": "sp"}, {"id": "36855035", "type": "test", "year": "2021", "stage": "1", "subject": "pol", "voivodeship": "mazowieckie", "school": "sp"}, {"id": "28807999", "type": "test", "year": "2021", "stage": "1", "subject": "ang", "voivodeship": "mazowieckie", "school": "sp"}, {"id": "96006989", "type": "test", "year": "2021", "stage": "1", "subject": "hip", "voivodeship": "mazowieckie", "school": "sp"}, {"id": "78249501", "type": "test", "year": "2021", "stage": "1", "subject": "nie", "voivodeship": "mazowieckie", "school": "sp"}, {"id": "28364547", "type": "test", "year": "2021", "stage": "1", "subject": "ros", "voivodeship": "mazowieckie", "school": "sp"}, {"id": "82473452", "type": "test", "year": "2021", "stage": "1", "subject": "fra", "voivodeship": "mazowieckie", "school": "sp"}, {"id": "78806945", "type": "test", "year": "2021", "stage": "1", "subject": "his", "voivodeship": "mazowieckie", "school": "sp"}, {"id": "53818377", "type": "test", "year": "2021", "stage": "1", "subject": "fiz", "voivodeship": "mazowieckie", "school": "sp"}, {"id": "73135870", "type": "test", "year": "2021", "stage": "1", "subject": "wos", "voivodeship": "mazowieckie", "school": "sp"}, {"id": "46889269", "type": "test", "year": "2021", "stage": "1", "subject": "che", "voivodeship": "mazowieckie", "school": "sp"}, {"id": "66180768", "type": "test", "year": "2021", "stage": "1", "subject": "bio", "voivodeship": "mazowieckie", "school": "sp"}, {"id": "53328015", "type": "test", "year": "2021", "stage": "1", "subject": "geo", "voivodeship": "mazowieckie", "school": "sp"}, {"id": "61509181", "type": "ans", "year": "2021", "stage": "1", "subject": "pol", "voivodeship": "mazowieckie", "school": "sp"}, {"id": "45957351", "type": "ans", "year": "2021", "stage": "1", "subject": "ang", "voivodeship": "mazowieckie", "school": "sp"}, {"id": "10534681", "type": "ans", "year": "2021", "stage": "1", "subject": "mat", "voivodeship": "mazowieckie", "school": "sp"}, {"id": "29292946", "type": "ans", "year": "2021", "stage": "1", "subject": "nie", "voivodeship": "mazowieckie", "school": "sp"}, {"id": "25854219", "type": "ans", "year": "2021", "stage": "1", "subject": "ros", "voivodeship": "mazowieckie", "school": "sp"}, {"id": "43577714", "type": "ans", "year": "2021", "stage": "1", "subject": "fra", "voivodeship": "mazowieckie", "school": "sp"}, {"id": "74486629", "type": "ans", "year": "2021", "stage": "1", "subject": "hip", "voivodeship": "mazowieckie", "school": "sp"}, {"id": "57443550", "type": "ans", "year": "2021", "stage": "1", "subject": "his", "voivodeship": "mazowieckie", "school": "sp"}, {"id": "91899280", "type": "ans", "year": "2021", "stage": "1", "subject": "fiz", "voivodeship": "mazowieckie", "school": "sp"}, {"id": "40134127", "type": "ans", "year": "2021", "stage": "1", "subject": "wos", "voivodeship": "mazowieckie", "school": "sp"}, {"id": "25900636", "type": "ans", "year": "2021", "stage": "1", "subject": "che", "voivodeship": "mazowieckie", "school": "sp"}, {"id": "40446175", "type": "ans", "year": "2021", "stage": "1", "subject": "bio", "voivodeship": "mazowieckie", "school": "sp"}, {"id": "70776212", "type": "ans", "year": "2021", "stage": "1", "subject": "geo", "voivodeship": "mazowieckie", "school": "sp"}, {"id": "79876963", "type": "test", "year": "2021", "stage": "2", "subject": "pol", "voivodeship": "mazowieckie", "school": "sp"}, {"id": "53849712", "type": "ans", "year": "2021", "stage": "2", "subject": "pol", "voivodeship": "mazowieckie", "school": "sp"}, {"id": "92068048", "type": "ans", "year": "2021", "stage": "2", "subject": "ang", "voivodeship": "mazowieckie", "school": "sp"}, {"id": "20656925", "type": "test", "year": "2021", "stage": "2", "subject": "ang", "voivodeship": "mazowieckie", "school": "sp"}, {"id": "87338360", "type": "test", "year": "2021", "stage": "2", "subject": "mat", "voivodeship": "mazowieckie", "school": "sp"}, {"id": "38019828", "type": "ans", "year": "2021", "stage": "2", "subject": "mat", "voivodeship": "mazowieckie", "school": "sp"}, {"id": "65442217", "type": "test", "year": "2021", "stage": "2", "subject": "nie", "voivodeship": "mazowieckie", "school": "sp"}, {"id": "14079019", "type": "ans", "year": "2021", "stage": "2", "subject": "nie", "voivodeship": "mazowieckie", "school": "sp"}, {"id": "43420874", "type": "test", "year": "2021", "stage": "2", "subject": "ros", "voivodeship": "mazowieckie", "school": "sp"}, {"id": "27128288", "type": "ans", "year": "2021", "stage": "2", "subject": "ros", "voivodeship": "mazowieckie", "school": "sp"}, {"id": "59916610", "type": "test", "year": "2021", "stage": "2", "subject": "fra", "voivodeship": "mazowieckie", "school": "sp"}, {"id": "90463595", "type": "ans", "year": "2021", "stage": "2", "subject": "fra", "voivodeship": "mazowieckie", "school": "sp"}, {"id": "63891835", "type": "test", "year": "2021", "stage": "2", "subject": "hip", "voivodeship": "mazowieckie", "school": "sp"}, {"id": "80909803", "type": "ans", "year": "2021", "stage": "2", "subject": "hip", "voivodeship": "mazowieckie", "school": "sp"}, {"id": "21649646", "type": "test", "year": "2021", "stage": "2", "subject": "his", "voivodeship": "mazowieckie", "school": "sp"}, {"id": "15466988", "type": "ans", "year": "2021", "stage": "2", "subject": "his", "voivodeship": "mazowieckie", "school": "sp"}, {"id": "39148027", "type": "test", "year": "2021", "stage": "2", "subject": "fiz", "voivodeship": "mazowieckie", "school": "sp"}, {"id": "42665213", "type": "ans", "year": "2021", "stage": "2", "subject": "fiz", "voivodeship": "mazowieckie", "school": "sp"}, {"id": "31102702", "type": "test", "year": "2021", "stage": "2", "subject": "wos", "voivodeship": "mazowieckie", "school": "sp"}, {"id": "24305105", "type": "ans", "year": "2021", "stage": "2", "subject": "wos", "voivodeship": "mazowieckie", "school": "sp"}, {"id": "67657282", "type": "test", "year": "2021", "stage": "2", "subject": "che", "voivodeship": "mazowieckie", "school": "sp"}, {"id": "29530765", "type": "ans", "year": "2021", "stage": "2", "subject": "che", "voivodeship": "mazowieckie", "school": "sp"}, {"id": "32882254", "type": "test", "year": "2021", "stage": "2", "subject": "bio", "voivodeship": "mazowieckie", "school": "sp"}, {"id": "11849528", "type": "ans", "year": "2021", "stage": "2", "subject": "bio", "voivodeship": "mazowieckie", "school": "sp"}, {"id": "47943297", "type": "test", "year": "2021", "stage": "2", "subject": "geo", "voivodeship": "mazowieckie", "school": "sp"}, {"id": "23039490", "type": "ans", "year": "2021", "stage": "2", "subject": "geo", "voivodeship": "mazowieckie", "school": "sp"}, {"id": "54890436", "type": "test", "year": "2021", "stage": "3", "subject": "pol", "voivodeship": "mazowieckie", "school": "sp"}, {"id": "43295888", "type": "ans", "year": "2021", "stage": "3", "subject": "pol", "voivodeship": "mazowieckie", "school": "sp"}, {"id": "79775170", "type": "test", "year": "2021", "stage": "3", "subject": "ang", "voivodeship": "mazowieckie", "school": "sp"}, {"id": "23568414", "type": "ans", "year": "2021", "stage": "3", "subject": "ang", "voivodeship": "mazowieckie", "school": "sp"}, {"id": "77936426", "type": "test", "year": "2021", "stage": "3", "subject": "mat", "voivodeship": "mazowieckie", "school": "sp"}, {"id": "88532730", "type": "ans", "year": "2021", "stage": "3", "subject": "mat", "voivodeship": "mazowieckie", "school": "sp"}, {"id": "17915469", "type": "test", "year": "2021", "stage": "3", "subject": "nie", "voivodeship": "mazowieckie", "school": "sp"}, {"id": "63181847", "type": "ans", "year": "2021", "stage": "3", "subject": "nie", "voivodeship": "mazowieckie", "school": "sp"}, {"id": "23238141", "type": "test", "year": "2021", "stage": "3", "subject": "ros", "voivodeship": "mazowieckie", "school": "sp"}, {"id": "84225366", "type": "ans", "year": "2021", "stage": "3", "subject": "ros", "voivodeship": "mazowieckie", "school": "sp"}, {"id": "39877861", "type": "test", "year": "2021", "stage": "3", "subject": "fra", "voivodeship": "mazowieckie", "school": "sp"}, {"id": "63333064", "type": "ans", "year": "2021", "stage": "3", "subject": "fra", "voivodeship": "mazowieckie", "school": "sp"}, {"id": "93341561", "type": "test", "year": "2021", "stage": "3", "subject": "hip", "voivodeship": "mazowieckie", "school": "sp"}, {"id": "38075454", "type": "ans", "year": "2021", "stage": "3", "subject": "hip", "voivodeship": "mazowieckie", "school": "sp"}, {"id": "87659339", "type": "test", "year": "2021", "stage": "3", "subject": "his", "voivodeship": "mazowieckie", "school": "sp"}, {"id": "17127108", "type": "ans", "year": "2021", "stage": "3", "subject": "his", "voivodeship": "mazowieckie", "school": "sp"}, {"id": "51210420", "type": "test", "year": "2021", "stage": "3", "subject": "fiz", "voivodeship": "mazowieckie", "school": "sp"}, {"id": "47478895", "type": "ans", "year": "2021", "stage": "3", "subject": "fiz", "voivodeship": "mazowieckie", "school": "sp"}, {"id": "82606329", "type": "test", "year": "2021", "stage": "3", "subject": "wos", "voivodeship": "mazowieckie", "school": "sp"}, {"id": "13726476", "type": "ans", "year": "2021", "stage": "3", "subject": "wos", "voivodeship": "mazowieckie", "school": "sp"}, {"id": "58326224", "type": "test", "year": "2021", "stage": "3", "subject": "che", "voivodeship": "mazowieckie", "school": "sp"}, {"id": "15198908", "type": "ans", "year": "2021", "stage": "3", "subject": "che", "voivodeship": "mazowieckie", "school": "sp"}, {"id": "55584013", "type": "test", "year": "2021", "stage": "3", "subject": "bio", "voivodeship": "mazowieckie", "school": "sp"}, {"id": "25025944", "type": "ans", "year": "2021", "stage": "3", "subject": "bio", "voivodeship": "mazowieckie", "school": "sp"}, {"id": "37640885", "type": "test", "year": "2021", "stage": "3", "subject": "geo", "voivodeship": "mazowieckie", "school": "sp"}, {"id": "60135389", "type": "ans", "year": "2021", "stage": "3", "subject": "geo", "voivodeship": "mazowieckie", "school": "sp"}, {"id": "77509662", "type": "test", "year": "2021", "stage": "1", "subject": "kwm", "voivodeship": "mazowieckie", "school": "sp"}, {"id": "23126096", "type": "ans", "year": "2021", "stage": "1", "subject": "kwm", "voivodeship": "mazowieckie", "school": "sp"}, {"id": "54202263", "type": "test", "year": "2021", "stage": "2", "subject": "kwm", "voivodeship": "mazowieckie", "school": "sp"}, {"id": "64859514", "type": "ans", "year": "2021", "stage": "2", "subject": "kwm", "voivodeship": "mazowieckie", "school": "sp"}, {"id": "77845993", "type": "test", "year": "2021", "stage": "3", "subject": "kwm", "voivodeship": "mazowieckie", "school": "sp"}, {"id": "18449879", "type": "ans", "year": "2021", "stage": "3", "subject": "kwm", "voivodeship": "mazowieckie", "school": "sp"}, {"id": "43394908", "type": "test", "year": "2022", "stage": "1", "subject": "fra", "voivodeship": "mazowieckie", "school": "sp"}, {"id": "46408084", "type": "test", "year": "2022", "stage": "1", "subject": "hip", "voivodeship": "mazowieckie", "school": "sp"}, {"id": "50674599", "type": "test", "year": "2022", "stage": "1", "subject": "nie", "voivodeship": "mazowieckie", "school": "sp"}, {"id": "87108220", "type": "test", "year": "2022", "stage": "1", "subject": "ang", "voivodeship": "mazowieckie", "school": "sp"}, {"id": "50970114", "type": "test", "year": "2022", "stage": "1", "subject": "geo", "voivodeship": "mazowieckie", "school": "sp"}, {"id": "90903462", "type": "test", "year": "2022", "stage": "1", "subject": "fiz", "voivodeship": "mazowieckie", "school": "sp"}, {"id": "56908679", "type": "test", "year": "2022", "stage": "1", "subject": "mat", "voivodeship": "mazowieckie", "school": "sp"}, {"id": "38340466", "type": "test", "year": "2022", "stage": "1", "subject": "his", "voivodeship": "mazowieckie", "school": "sp"}, {"id": "84913319", "type": "test", "year": "2022", "stage": "1", "subject": "che", "voivodeship": "mazowieckie", "school": "sp"}, {"id": "90923755", "type": "test", "year": "2022", "stage": "1", "subject": "bio", "voivodeship": "mazowieckie", "school": "sp"}, {"id": "58278239", "type": "test", "year": "2022", "stage": "1", "subject": "pol", "voivodeship": "mazowieckie", "school": "sp"}, {"id": "65359895", "type": "ans", "year": "2022", "stage": "1", "subject": "fra", "voivodeship": "mazowieckie", "school": "sp"}, {"id": "65243032", "type": "ans", "year": "2022", "stage": "1", "subject": "hip", "voivodeship": "mazowieckie", "school": "sp"}, {"id": "27852984", "type": "ans", "year": "2022", "stage": "1", "subject": "nie", "voivodeship": "mazowieckie", "school": "sp"}, {"id": "18688801", "type": "ans", "year": "2022", "stage": "1", "subject": "ang", "voivodeship": "mazowieckie", "school": "sp"}, {"id": "28183660", "type": "ans", "year": "2022", "stage": "1", "subject": "geo", "voivodeship": "mazowieckie", "school": "sp"}, {"id": "79315695", "type": "ans", "year": "2022", "stage": "1", "subject": "fiz", "voivodeship": "mazowieckie", "school": "sp"}, {"id": "19849993", "type": "ans", "year": "2022", "stage": "1", "subject": "mat", "voivodeship": "mazowieckie", "school": "sp"}, {"id": "46637831", "type": "ans", "year": "2022", "stage": "1", "subject": "his", "voivodeship": "mazowieckie", "school": "sp"}, {"id": "91547801", "type": "ans", "year": "2022", "stage": "1", "subject": "che", "voivodeship": "mazowieckie", "school": "sp"}, {"id": "82980107", "type": "ans", "year": "2022", "stage": "1", "subject": "bio", "voivodeship": "mazowieckie", "school": "sp"}, {"id": "52373888", "type": "ans", "year": "2022", "stage": "1", "subject": "pol", "voivodeship": "mazowieckie", "school": "sp"}, {"id": "10458832", "type": "ans", "year": "2022", "stage": "2", "subject": "ang", "voivodeship": "mazowieckie", "school": "sp"}, {"id": "61573699", "type": "ans", "year": "2022", "stage": "2", "subject": "nie", "voivodeship": "mazowieckie", "school": "sp"}, {"id": "25725735", "type": "ans", "year": "2022", "stage": "2", "subject": "fra", "voivodeship": "mazowieckie", "school": "sp"}, {"id": "97407335", "type": "ans", "year": "2022", "stage": "2", "subject": "hip", "voivodeship": "mazowieckie", "school": "sp"}, {"id": "98330211", "type": "test", "year": "2022", "stage": "2", "subject": "hip", "voivodeship": "mazowieckie", "school": "sp"}, {"id": "58426129", "type": "test", "year": "2022", "stage": "2", "subject": "fra", "voivodeship": "mazowieckie", "school": "sp"}, {"id": "42231145", "type": "test", "year": "2022", "stage": "2", "subject": "nie", "voivodeship": "mazowieckie", "school": "sp"}, {"id": "47708207", "type": "test", "year": "2022", "stage": "2", "subject": "ang", "voivodeship": "mazowieckie", "school": "sp"}, {"id": "80499309", "type": "test", "year": "2022", "stage": "2", "subject": "geo", "voivodeship": "mazowieckie", "school": "sp"}, {"id": "41524432", "type": "test", "year": "2022", "stage": "2", "subject": "fiz", "voivodeship": "mazowieckie", "school": "sp"}, {"id": "53675652", "type": "ans", "year": "2022", "stage": "2", "subject": "fiz", "voivodeship": "mazowieckie", "school": "sp"}, {"id": "62342737", "type": "ans", "year": "2022", "stage": "2", "subject": "geo", "voivodeship": "mazowieckie", "school": "sp"}, {"id": "82715136", "type": "ans", "year": "2022", "stage": "2", "subject": "mat", "voivodeship": "mazowieckie", "school": "sp"}, {"id": "88632855", "type": "test", "year": "2022", "stage": "2", "subject": "mat", "voivodeship": "mazowieckie", "school": "sp"}, {"id": "91830726", "type": "test", "year": "2022", "stage": "2", "subject": "his", "voivodeship": "mazowieckie", "school": "sp"}, {"id": "88610775", "type": "ans", "year": "2022", "stage": "2", "subject": "his", "voivodeship": "mazowieckie", "school": "sp"}, {"id": "77752281", "type": "test", "year": "2022", "stage": "2", "subject": "che", "voivodeship": "mazowieckie", "school": "sp"}, {"id": "87945871", "type": "ans", "year": "2022", "stage": "2", "subject": "che", "voivodeship": "mazowieckie", "school": "sp"}, {"id": "73755790", "type": "ans", "year": "2022", "stage": "2", "subject": "bio", "voivodeship": "mazowieckie", "school": "sp"}, {"id": "91406728", "type": "test", "year": "2022", "stage": "2", "subject": "bio", "voivodeship": "mazowieckie", "school": "sp"}, {"id": "98447304", "type": "test", "year": "2022", "stage": "2", "subject": "pol", "voivodeship": "mazowieckie", "school": "sp"}, {"id": "75123619", "type": "ans", "year": "2022", "stage": "2", "subject": "pol", "voivodeship": "mazowieckie", "school": "sp"}, {"id": "96632111", "type": "ans", "year": "2022", "stage": "1", "subject": "kwm", "voivodeship": "mazowieckie", "school": "sp"}, {"id": "54657920", "type": "test", "year": "2022", "stage": "1", "subject": "kwm", "voivodeship": "mazowieckie", "school": "sp"}, {"id": "28984354", "type": "ans", "year": "2022", "stage": "3", "subject": "nie", "voivodeship": "mazowieckie", "school": "sp"}, {"id": "15583689", "type": "ans", "year": "2022", "stage": "3", "subject": "fra", "voivodeship": "mazowieckie", "school": "sp"}, {"id": "88058382", "type": "ans", "year": "2022", "stage": "3", "subject": "hip", "voivodeship": "mazowieckie", "school": "sp"}, {"id": "66192334", "type": "test", "year": "2022", "stage": "3", "subject": "nie", "voivodeship": "mazowieckie", "school": "sp"}, {"id": "95775425", "type": "test", "year": "2022", "stage": "3", "subject": "fra", "voivodeship": "mazowieckie", "school": "sp"}, {"id": "82294566", "type": "test", "year": "2022", "stage": "3", "subject": "hip", "voivodeship": "mazowieckie", "school": "sp"}, {"id": "41396520", "type": "test", "year": "2022", "stage": "3", "subject": "ang", "voivodeship": "mazowieckie", "school": "sp"}, {"id": "51828470", "type": "ans", "year": "2022", "stage": "3", "subject": "ang", "voivodeship": "mazowieckie", "school": "sp"}, {"id": "84468599", "type": "test", "year": "2022", "stage": "3", "subject": "mat", "voivodeship": "mazowieckie", "school": "sp"}, {"id": "33899249", "type": "ans", "year": "2022", "stage": "3", "subject": "mat", "voivodeship": "mazowieckie", "school": "sp"}, {"id": "86978401", "type": "test", "year": "2022", "stage": "3", "subject": "geo", "voivodeship": "mazowieckie", "school": "sp"}, {"id": "19286913", "type": "ans", "year": "2022", "stage": "3", "subject": "geo", "voivodeship": "mazowieckie", "school": "sp"}, {"id": "17891178", "type": "test", "year": "2022", "stage": "3", "subject": "fiz", "voivodeship": "mazowieckie", "school": "sp"}, {"id": "61719069", "type": "ans", "year": "2022", "stage": "3", "subject": "fiz", "voivodeship": "mazowieckie", "school": "sp"}, {"id": "93892422", "type": "test", "year": "2022", "stage": "3", "subject": "che", "voivodeship": "mazowieckie", "school": "sp"}, {"id": "41952495", "type": "ans", "year": "2022", "stage": "3", "subject": "che", "voivodeship": "mazowieckie", "school": "sp"}, {"id": "37940835", "type": "test", "year": "2022", "stage": "3", "subject": "his", "voivodeship": "mazowieckie", "school": "sp"}, {"id": "18465664", "type": "ans", "year": "2022", "stage": "3", "subject": "his", "voivodeship": "mazowieckie", "school": "sp"}, {"id": "38886711", "type": "ans", "year": "2022", "stage": "3", "subject": "bio", "voivodeship": "mazowieckie", "school": "sp"}, {"id": "80054013", "type": "test", "year": "2022", "stage": "3", "subject": "bio", "voivodeship": "mazowieckie", "school": "sp"}, {"id": "46160506", "type": "test", "year": "2022", "stage": "3", "subject": "pol", "voivodeship": "mazowieckie", "school": "sp"}, {"id": "87437411", "type": "ans", "year": "2022", "stage": "3", "subject": "pol", "voivodeship": "mazowieckie", "school": "sp"}, {"id": "49079330", "type": "ans", "year": "2022", "stage": "2", "subject": "kwm", "voivodeship": "mazowieckie", "school": "sp"}, {"id": "41711338", "type": "test", "year": "2022", "stage": "2", "subject": "kwm", "voivodeship": "mazowieckie", "school": "sp"}, {"voivodeship": "lodzkie", "subject": "nie", "type": "ans", "stage": "1", "year": "2023", "id": "66851471", "school": "sp"}, {"voivodeship": "lodzkie", "subject": "hip", "type": "ans", "stage": "1", "year": "2023", "id": "86897848", "school": "sp"}, {"voivodeship": "lodzkie", "subject": "bio", "type": "test", "stage": "1", "year": "2023", "id": "76513557", "school": "sp"}, {"voivodeship": "lodzkie", "subject": "fra", "type": "test", "stage": "1", "year": "2023", "id": "39765826", "school": "sp"}, {"voivodeship": "lodzkie", "subject": "fiz", "type": "test", "stage": "1", "year": "2023", "id": "26509622", "school": "sp"}, {"voivodeship": "lodzkie", "subject": "his", "type": "test", "stage": "1", "year": "2023", "id": "77485615", "school": "sp"}, {"voivodeship": "lodzkie", "subject": "his", "type": "ans", "stage": "1", "year": "2023", "id": "17411631", "school": "sp"}, {"voivodeship": "lodzkie", "subject": "che", "type": "ans", "stage": "1", "year": "2023", "id": "99685929", "school": "sp"}, {"voivodeship": "lodzkie", "subject": "nie", "type": "test", "stage": "1", "year": "2023", "id": "67098049", "school": "sp"}, {"voivodeship": "lodzkie", "subject": "bio", "type": "ans", "stage": "1", "year": "2023", "id": "78601598", "school": "sp"}, {"voivodeship": "lodzkie", "subject": "pol", "type": "ans", "stage": "1", "year": "2023", "id": "32574114", "school": "sp"}, {"voivodeship": "lodzkie", "subject": "ang", "type": "ans", "stage": "1", "year": "2023", "id": "75260616", "school": "sp"}, {"voivodeship": "lodzkie", "subject": "che", "type": "test", "stage": "1", "year": "2023", "id": "81763031", "school": "sp"}, {"voivodeship": "lodzkie", "subject": "geo", "type": "test", "stage": "1", "year": "2023", "id": "10651547", "school": "sp"}, {"voivodeship": "lodzkie", "subject": "mat", "type": "test", "stage": "1", "year": "2023", "id": "61800926", "school": "sp"}, {"voivodeship": "lodzkie", "subject": "mat", "type": "ans", "stage": "1", "year": "2023", "id": "70787131", "school": "sp"}, {"voivodeship": "lodzkie", "subject": "geo", "type": "ans", "stage": "1", "year": "2023", "id": "82805411", "school": "sp"}, {"voivodeship": "lodzkie", "subject": "pol", "type": "test", "stage": "1", "year": "2023", "id": "62570536", "school": "sp"}, {"voivodeship": "lodzkie", "subject": "fra", "type": "ans", "stage": "1", "year": "2023", "id": "52323441", "school": "sp"}, {"voivodeship": "lodzkie", "subject": "ang", "type": "test", "stage": "1", "year": "2023", "id": "85155580", "school": "sp"}, {"voivodeship": "lodzkie", "subject": "fiz", "type": "ans", "stage": "1", "year": "2023", "id": "89683680", "school": "sp"}, {"voivodeship": "lodzkie", "subject": "hip", "type": "test", "stage": "1", "year": "2023", "id": "34405527", "school": "sp"}, {"id": "83156607", "subject": "bio", "stage": "1", "year": "2023", "school": "sp", "type": "test", "voivodeship": "mazowieckie"}, {"id": "79248554", "subject": "che", "stage": "1", "year": "2023", "school": "sp", "type": "test", "voivodeship": "mazowieckie"}, {"id": "50930012", "subject": "fiz", "stage": "1", "year": "2023", "school": "sp", "type": "test", "voivodeship": "mazowieckie"}, {"id": "66122946", "subject": "his", "stage": "1", "year": "2023", "school": "sp", "type": "test", "voivodeship": "mazowieckie"}, {"id": "97867732", "subject": "geo", "stage": "1", "year": "2023", "school": "sp", "type": "test", "voivodeship": "mazowieckie"}, {"id": "13207594", "subject": "mat", "stage": "1", "year": "2023", "school": "sp", "type": "test", "voivodeship": "mazowieckie"}, {"id": "52964828", "subject": "pol", "stage": "1", "year": "2023", "school": "sp", "type": "test", "voivodeship": "mazowieckie"}, {"id": "60957110", "subject": "bio", "stage": "1", "year": "2023", "school": "sp", "type": "ans", "voivodeship": "mazowieckie"}, {"id": "87910041", "subject": "che", "stage": "1", "year": "2023", "school": "sp", "type": "ans", "voivodeship": "mazowieckie"}, {"id": "19214049", "subject": "fiz", "stage": "1", "year": "2023", "school": "sp", "type": "ans", "voivodeship": "mazowieckie"}, {"id": "63201339", "subject": "geo", "stage": "1", "year": "2023", "school": "sp", "type": "ans", "voivodeship": "mazowieckie"}, {"id": "70582597", "subject": "his", "stage": "1", "year": "2023", "school": "sp", "type": "ans", "voivodeship": "mazowieckie"}, {"id": "86308352", "subject": "mat", "stage": "1", "year": "2023", "school": "sp", "type": "ans", "voivodeship": "mazowieckie"}, {"id": "39857632", "subject": "pol", "stage": "1", "year": "2023", "school": "sp", "type": "ans", "voivodeship": "mazowieckie"}, {"id": "77504663", "subject": "nie", "stage": "1", "year": "2023", "school": "sp", "type": "test", "voivodeship": "mazowieckie"}, {"id": "67388985", "subject": "ang", "stage": "1", "year": "2023", "school": "sp", "type": "test", "voivodeship": "mazowieckie"}, {"id": "48432045", "subject": "fra", "stage": "1", "year": "2023", "school": "sp", "type": "test", "voivodeship": "mazowieckie"}, {"id": "28050844", "subject": "hip", "stage": "1", "year": "2023", "school": "sp", "type": "test", "voivodeship": "mazowieckie"}, {"id": "66992144", "subject": "hip", "stage": "1", "year": "2023", "school": "sp", "type": "ans", "voivodeship": "mazowieckie"}, {"id": "96384358", "subject": "fra", "stage": "1", "year": "2023", "school": "sp", "type": "ans", "voivodeship": "mazowieckie"}, {"id": "80511271", "subject": "nie", "stage": "1", "year": "2023", "school": "sp", "type": "ans", "voivodeship": "mazowieckie"}, {"id": "73416655", "subject": "ang", "stage": "1", "year": "2023", "school": "sp", "type": "ans", "voivodeship": "mazowieckie"}, {"id": "72255639", "subject": "fra", "stage": "2", "year": "2023", "school": "sp", "type": "ans", "voivodeship": "mazowieckie"}, {"id": "14843887", "subject": "nie", "stage": "2", "year": "2023", "school": "sp", "type": "ans", "voivodeship": "mazowieckie"}, {"id": "92063307", "subject": "hip", "stage": "2", "year": "2023", "school": "sp", "type": "ans", "voivodeship": "mazowieckie"}, {"id": "56219714", "subject": "hip", "stage": "2", "year": "2023", "school": "sp", "type": "test", "voivodeship": "mazowieckie"}, {"id": "68578911", "subject": "fra", "stage": "2", "year": "2023", "school": "sp", "type": "test", "voivodeship": "mazowieckie"}, {"id": "26797469", "subject": "nie", "stage": "2", "year": "2023", "school": "sp", "type": "test", "voivodeship": "mazowieckie"}, {"id": "97468546", "subject": "che", "stage": "2", "year": "2023", "school": "sp", "type": "test", "voivodeship": "mazowieckie"}, {"id": "43627528", "subject": "che", "stage": "2", "year": "2023", "school": "sp", "type": "ans", "voivodeship": "mazowieckie"}, {"id": "11822657", "subject": "geo", "stage": "2", "year": "2023", "school": "sp", "type": "test", "voivodeship": "mazowieckie"}, {"id": "63091853", "subject": "geo", "stage": "2", "year": "2023", "school": "sp", "type": "ans", "voivodeship": "mazowieckie"}, {"id": "67395739", "subject": "ang", "stage": "2", "year": "2023", "school": "sp", "type": "test", "voivodeship": "mazowieckie"}, {"id": "79283432", "subject": "ang", "stage": "2", "year": "2023", "school": "sp", "type": "ans", "voivodeship": "mazowieckie"}, {"id": "13404530", "subject": "mat", "stage": "2", "year": "2023", "school": "sp", "type": "test", "voivodeship": "mazowieckie"}, {"id": "37095866", "subject": "mat", "stage": "2", "year": "2023", "school": "sp", "type": "ans", "voivodeship": "mazowieckie"}, {"id": "76375072", "subject": "his", "stage": "2", "year": "2023", "school": "sp", "type": "ans", "voivodeship": "mazowieckie"}, {"id": "10734715", "subject": "his", "stage": "2", "year": "2023", "school": "sp", "type": "test", "voivodeship": "mazowieckie"}, {"id": "46179190", "subject": "bio", "stage": "2", "year": "2023", "school": "sp", "type": "ans", "voivodeship": "mazowieckie"}, {"id": "57776451", "subject": "bio", "stage": "2", "year": "2023", "school": "sp", "type": "test", "voivodeship": "mazowieckie"}, {"id": "10713039", "subject": "pol", "stage": "2", "year": "2023", "school": "sp", "type": "ans", "voivodeship": "mazowieckie"}, {"id": "88795109", "subject": "pol", "stage": "2", "year": "2023", "school": "sp", "type": "test", "voivodeship": "mazowieckie"}, {"id": "71373639", "subject": "fiz", "stage": "2", "year": "2023", "school": "sp", "type": "test", "voivodeship": "mazowieckie"}, {"id": "94743644", "subject": "fiz", "stage": "2", "year": "2023", "school": "sp", "type": "ans", "voivodeship": "mazowieckie"}]